{
  "data": {
    "mediaData": {
      "edges": [
        {
          "node": {
            "thread_items": [
              {
                "post": {
                  "user": {
                    "profile_pic_url": "https://scontent.cdninstagram.com/v/t51.2885-19/358342896_134138973038748_2871278261242540091_n.jpg?stp=dst-jpg_s150x150&_nc_ht=scontent.cdninstagram.com&_nc_cat=100&_nc_ohc=fnBk02x8fYYAX8m4UPS&edm=APs17CUBAAAA&ccb=7-5&oh=00_AfA9CiG3KzCtGkFuFfszkuUxpvtz7Btl_s53wbX5i2ADsw&oe=6531BE5A&_nc_sid=10d13b",
                    "username": "battlenet",
                    "friendship_status": {
                      "following": false,
                      "muting": false,
                      "blocking": null
                    },
                    "pk": "45512948387",
                    "transparency_label": null,
                    "transparency_product": null,
                    "transparency_product_enabled": false,
                    "is_verified": true,
                    "id": null,
                    "text_post_app_is_private": false
                  },
                  "accessibility_caption": "Photo by Battle.net on July 19, 2023. May be a video game screenshot.",
                  "image_versions2": {
                    "candidates": [
                      {
                        "height": 1080,
                        "url": "https://scontent.cdninstagram.com/v/t51.2885-15/361683841_1269686787272133_3455125100069940091_n.jpg?stp=dst-jpg_e35&efg=eyJ2ZW5jb2RlX3RhZyI6ImltYWdlX3VybGdlbi4xOTIweDEwODAuc2RyIn0&_nc_ht=scontent.cdninstagram.com&_nc_cat=109&_nc_ohc=gvlUCsqDi30AX-Ay2lm&edm=APs17CUBAAAA&ccb=7-5&ig_cache_key=MzE1MDU5ODM2NTA4NDYxMTUxMg%3D%3D.2-ccb7-5&oh=00_AfCDsowK-Tnu7RBaBCDSVQpnPtlWSuCgdawDk_pTo4usTA&oe=653087C0&_nc_sid=10d13b",
                        "width": 1920
                      },
                      {
                        "height": 608,
                        "url": "https://scontent.cdninstagram.com/v/t51.2885-15/361683841_1269686787272133_3455125100069940091_n.jpg?stp=dst-jpg_e35_s1080x1080&efg=eyJ2ZW5jb2RlX3RhZyI6ImltYWdlX3VybGdlbi4xOTIweDEwODAuc2RyIn0&_nc_ht=scontent.cdninstagram.com&_nc_cat=109&_nc_ohc=gvlUCsqDi30AX-Ay2lm&edm=APs17CUBAAAA&ccb=7-5&ig_cache_key=MzE1MDU5ODM2NTA4NDYxMTUxMg%3D%3D.2-ccb7-5&oh=00_AfBS8tPs-vkxxn9KTkJWiz4BOuZHcbiim0iY4SV5VZjcGw&oe=653087C0&_nc_sid=10d13b",
                        "width": 1080
                      },
                      {
                        "height": 405,
                        "url": "https://scontent.cdninstagram.com/v/t51.2885-15/361683841_1269686787272133_3455125100069940091_n.jpg?stp=dst-jpg_e35_s720x720&efg=eyJ2ZW5jb2RlX3RhZyI6ImltYWdlX3VybGdlbi4xOTIweDEwODAuc2RyIn0&_nc_ht=scontent.cdninstagram.com&_nc_cat=109&_nc_ohc=gvlUCsqDi30AX-Ay2lm&edm=APs17CUBAAAA&ccb=7-5&ig_cache_key=MzE1MDU5ODM2NTA4NDYxMTUxMg%3D%3D.2-ccb7-5&oh=00_AfBcT1vCO37I1nwjHmzoiPyJMZlXtn7i2QRxLJzABU0DNg&oe=653087C0&_nc_sid=10d13b",
                        "width": 720
                      },
                      {
                        "height": 360,
                        "url": "https://scontent.cdninstagram.com/v/t51.2885-15/361683841_1269686787272133_3455125100069940091_n.jpg?stp=dst-jpg_e35_s640x640_sh0.08&efg=eyJ2ZW5jb2RlX3RhZyI6ImltYWdlX3VybGdlbi4xOTIweDEwODAuc2RyIn0&_nc_ht=scontent.cdninstagram.com&_nc_cat=109&_nc_ohc=gvlUCsqDi30AX-Ay2lm&edm=APs17CUBAAAA&ccb=7-5&ig_cache_key=MzE1MDU5ODM2NTA4NDYxMTUxMg%3D%3D.2-ccb7-5&oh=00_AfBQ0ihEaAKDX6tZ_8GMVBad5ZMC9o_dUVMyUDcOnoIggA&oe=653087C0&_nc_sid=10d13b",
                        "width": 640
                      },
                      {
                        "height": 270,
                        "url": "https://scontent.cdninstagram.com/v/t51.2885-15/361683841_1269686787272133_3455125100069940091_n.jpg?stp=dst-jpg_e35_s480x480&efg=eyJ2ZW5jb2RlX3RhZyI6ImltYWdlX3VybGdlbi4xOTIweDEwODAuc2RyIn0&_nc_ht=scontent.cdninstagram.com&_nc_cat=109&_nc_ohc=gvlUCsqDi30AX-Ay2lm&edm=APs17CUBAAAA&ccb=7-5&ig_cache_key=MzE1MDU5ODM2NTA4NDYxMTUxMg%3D%3D.2-ccb7-5&oh=00_AfBvmkh6sXu1ZOB-IUukv2Fuaq8hI--X553zsSDhYAA32g&oe=653087C0&_nc_sid=10d13b",
                        "width": 480
                      },
                      {
                        "height": 180,
                        "url": "https://scontent.cdninstagram.com/v/t51.2885-15/361683841_1269686787272133_3455125100069940091_n.jpg?stp=dst-jpg_e35_s320x320&efg=eyJ2ZW5jb2RlX3RhZyI6ImltYWdlX3VybGdlbi4xOTIweDEwODAuc2RyIn0&_nc_ht=scontent.cdninstagram.com&_nc_cat=109&_nc_ohc=gvlUCsqDi30AX-Ay2lm&edm=APs17CUBAAAA&ccb=7-5&ig_cache_key=MzE1MDU5ODM2NTA4NDYxMTUxMg%3D%3D.2-ccb7-5&oh=00_AfA9Vk8KD3mHeez6e0TvcAc74pCLRqVHRP1PeDjyGxhOCQ&oe=653087C0&_nc_sid=10d13b",
                        "width": 320
                      },
                      {
                        "height": 135,
                        "url": "https://scontent.cdninstagram.com/v/t51.2885-15/361683841_1269686787272133_3455125100069940091_n.jpg?stp=dst-jpg_e35_s240x240&efg=eyJ2ZW5jb2RlX3RhZyI6ImltYWdlX3VybGdlbi4xOTIweDEwODAuc2RyIn0&_nc_ht=scontent.cdninstagram.com&_nc_cat=109&_nc_ohc=gvlUCsqDi30AX-Ay2lm&edm=APs17CUBAAAA&ccb=7-5&ig_cache_key=MzE1MDU5ODM2NTA4NDYxMTUxMg%3D%3D.2-ccb7-5&oh=00_AfDtTHkKMBlh55s9o9CpwrLb9uJU0eyx10K4OhjWydXArQ&oe=653087C0&_nc_sid=10d13b",
                        "width": 240
                      },
                      {
                        "height": 1080,
                        "url": "https://scontent.cdninstagram.com/v/t51.2885-15/361683841_1269686787272133_3455125100069940091_n.jpg?stp=c420.0.1080.1080a_dst-jpg_e35_s1080x1080&efg=eyJ2ZW5jb2RlX3RhZyI6ImltYWdlX3VybGdlbi4xOTIweDEwODAuc2RyIn0&_nc_ht=scontent.cdninstagram.com&_nc_cat=109&_nc_ohc=gvlUCsqDi30AX-Ay2lm&edm=APs17CUBAAAA&ccb=7-5&ig_cache_key=MzE1MDU5ODM2NTA4NDYxMTUxMg%3D%3D.2-ccb7-5&oh=00_AfDqQx4Kr8gG6ZO_qKsV5izwvWoh2tsxvl2kicUJIQE5Fg&oe=653087C0&_nc_sid=10d13b",
                        "width": 1080
                      },
                      {
                        "height": 750,
                        "url": "https://scontent.cdninstagram.com/v/t51.2885-15/361683841_1269686787272133_3455125100069940091_n.jpg?stp=c420.0.1080.1080a_dst-jpg_e35_s750x750_sh0.08&efg=eyJ2ZW5jb2RlX3RhZyI6ImltYWdlX3VybGdlbi4xOTIweDEwODAuc2RyIn0&_nc_ht=scontent.cdninstagram.com&_nc_cat=109&_nc_ohc=gvlUCsqDi30AX-Ay2lm&edm=APs17CUBAAAA&ccb=7-5&ig_cache_key=MzE1MDU5ODM2NTA4NDYxMTUxMg%3D%3D.2-ccb7-5&oh=00_AfAuys1cZDcH7QgExBWLWAApwVwQe24NHHcG05khLUOxBw&oe=653087C0&_nc_sid=10d13b",
                        "width": 750
                      },
                      {
                        "height": 640,
                        "url": "https://scontent.cdninstagram.com/v/t51.2885-15/361683841_1269686787272133_3455125100069940091_n.jpg?stp=c420.0.1080.1080a_dst-jpg_e35_s640x640_sh0.08&efg=eyJ2ZW5jb2RlX3RhZyI6ImltYWdlX3VybGdlbi4xOTIweDEwODAuc2RyIn0&_nc_ht=scontent.cdninstagram.com&_nc_cat=109&_nc_ohc=gvlUCsqDi30AX-Ay2lm&edm=APs17CUBAAAA&ccb=7-5&ig_cache_key=MzE1MDU5ODM2NTA4NDYxMTUxMg%3D%3D.2-ccb7-5&oh=00_AfCCglCInIVmAtl7dcP493NJ-cuw_NrGG2yXz0NLw7BFfA&oe=653087C0&_nc_sid=10d13b",
                        "width": 640
                      },
                      {
                        "height": 480,
                        "url": "https://scontent.cdninstagram.com/v/t51.2885-15/361683841_1269686787272133_3455125100069940091_n.jpg?stp=c420.0.1080.1080a_dst-jpg_e35_s480x480&efg=eyJ2ZW5jb2RlX3RhZyI6ImltYWdlX3VybGdlbi4xOTIweDEwODAuc2RyIn0&_nc_ht=scontent.cdninstagram.com&_nc_cat=109&_nc_ohc=gvlUCsqDi30AX-Ay2lm&edm=APs17CUBAAAA&ccb=7-5&ig_cache_key=MzE1MDU5ODM2NTA4NDYxMTUxMg%3D%3D.2-ccb7-5&oh=00_AfCyr7wyW42NQTLuQKxXVGN_YDEu6mQuhSKR7f2jbHkmOg&oe=653087C0&_nc_sid=10d13b",
                        "width": 480
                      },
                      {
                        "height": 320,
                        "url": "https://scontent.cdninstagram.com/v/t51.2885-15/361683841_1269686787272133_3455125100069940091_n.jpg?stp=c420.0.1080.1080a_dst-jpg_e35_s320x320&efg=eyJ2ZW5jb2RlX3RhZyI6ImltYWdlX3VybGdlbi4xOTIweDEwODAuc2RyIn0&_nc_ht=scontent.cdninstagram.com&_nc_cat=109&_nc_ohc=gvlUCsqDi30AX-Ay2lm&edm=APs17CUBAAAA&ccb=7-5&ig_cache_key=MzE1MDU5ODM2NTA4NDYxMTUxMg%3D%3D.2-ccb7-5&oh=00_AfC_t36hXRkyAwUPEti0fsfABvO0g5pCWWywvT19-id9SA&oe=653087C0&_nc_sid=10d13b",
                        "width": 320
                      },
                      {
                        "height": 240,
                        "url": "https://scontent.cdninstagram.com/v/t51.2885-15/361683841_1269686787272133_3455125100069940091_n.jpg?stp=c420.0.1080.1080a_dst-jpg_e35_s240x240&efg=eyJ2ZW5jb2RlX3RhZyI6ImltYWdlX3VybGdlbi4xOTIweDEwODAuc2RyIn0&_nc_ht=scontent.cdninstagram.com&_nc_cat=109&_nc_ohc=gvlUCsqDi30AX-Ay2lm&edm=APs17CUBAAAA&ccb=7-5&ig_cache_key=MzE1MDU5ODM2NTA4NDYxMTUxMg%3D%3D.2-ccb7-5&oh=00_AfDd5t6dFcmdANryLrK1ZgFCdPWSKsUB_2qPtvnKRNVrOg&oe=653087C0&_nc_sid=10d13b",
                        "width": 240
                      },
                      {
                        "height": 150,
                        "url": "https://scontent.cdninstagram.com/v/t51.2885-15/361683841_1269686787272133_3455125100069940091_n.jpg?stp=c420.0.1080.1080a_dst-jpg_e35_s150x150&efg=eyJ2ZW5jb2RlX3RhZyI6ImltYWdlX3VybGdlbi4xOTIweDEwODAuc2RyIn0&_nc_ht=scontent.cdninstagram.com&_nc_cat=109&_nc_ohc=gvlUCsqDi30AX-Ay2lm&edm=APs17CUBAAAA&ccb=7-5&ig_cache_key=MzE1MDU5ODM2NTA4NDYxMTUxMg%3D%3D.2-ccb7-5&oh=00_AfAhXc2pB0DdR55wS8HJjYC5nZ2ipExGYUkM2iW559yptA&oe=653087C0&_nc_sid=10d13b",
                        "width": 150
                      }
                    ]
                  },
                  "original_width": 1920,
                  "original_height": 1080,
                  "code": "Cu5LIU8y3O4",
                  "video_versions": null,
                  "carousel_media": null,
                  "pk": "3150598365084611512",
                  "text_post_app_info": {
                    "share_info": {
                      "can_quote_post": true,
                      "can_repost": true,
                      "is_reposted_by_viewer": false,
                      "repost_restricted_reason": null,
                      "__typename": "XDTShareInfo",
                      "reposted_post": null,
                      "quoted_post": null
                    },
                    "can_reply": true,
                    "is_reply": false,
                    "hush_info": null,
                    "reply_control": "everyone",
                    "pinned_post_info": null,
                    "link_preview_attachment": null,
                    "reply_to_author": null,
                    "is_post_unavailable": false,
                    "post_unavailable_reason": null
                  },
                  "is_fb_only": null,
                  "is_internal_only": null,
                  "id": "3150598365084611512_45512948387",
                  "media_type": 1,
                  "has_audio": null,
                  "audio": null,
                  "transcription_data": null,
                  "caption_is_edited": false,
                  "has_liked": false,
                  "is_paid_partnership": null,
                  "like_and_view_counts_disabled": false,
                  "taken_at": 1689800614,
                  "caption": {
                    "text": "What's everyone's favorite World of Warcraft zone?\n\nWe'll start with ours ðŸŒ²"
                  },
                  "like_count": 228,
                  "media_overlay_info": null
                },
                "line_type": "line",
                "view_replies_cta_string": "70 respuestas",
                "reply_facepile_users": [
                  {
                    "__typename": "XDTUserDict",
                    "id": null,
                    "profile_pic_url": "https://scontent.cdninstagram.com/v/t51.2885-19/361329770_974598767183910_4721884889008870691_n.jpg?stp=dst-jpg_s150x150&_nc_ht=scontent.cdninstagram.com&_nc_cat=106&_nc_ohc=vuuyEHzfIyoAX8NJpyo&edm=APs17CUBAAAA&ccb=7-5&oh=00_AfBOoc8G1fZTcX0wBBkx0zC9p4V6WADmzKtaO4zo0yMiQw&oe=65331D0F&_nc_sid=10d13b"
                  },
                  {
                    "__typename": "XDTUserDict",
                    "id": null,
                    "profile_pic_url": "https://scontent.cdninstagram.com/v/t51.2885-19/358363512_2166376493752026_3194067303060368211_n.jpg?stp=dst-jpg_s150x150&_nc_ht=scontent.cdninstagram.com&_nc_cat=106&_nc_ohc=JzI_y6QlxXwAX8rzpHr&edm=APs17CUBAAAA&ccb=7-5&oh=00_AfBQoihKtSMe_MFmHzzGE7cWTRixPiSihtcUmFgPdkBlNw&oe=6532C282&_nc_sid=10d13b"
                  },
                  {
                    "__typename": "XDTUserDict",
                    "id": null,
                    "profile_pic_url": "https://scontent.cdninstagram.com/v/t51.2885-19/358185320_1335733087320254_5725399269523358910_n.jpg?stp=dst-jpg_s150x150&_nc_ht=scontent.cdninstagram.com&_nc_cat=102&_nc_ohc=7O9Js8jSfvIAX-gVwji&edm=APs17CUBAAAA&ccb=7-5&oh=00_AfBXYpy6KhrmUThSUvtx1AQxzJjOLkmESLbIS6Q5-QybfQ&oe=6532230A&_nc_sid=10d13b"
                  }
                ],
                "should_show_replies_cta": true,
                "__typename": "XDTThreadItem"
              }
            ],
            "id": "3150598365084611512",
            "__typename": "XDTThread"
          },
          "__typename": "XDTUserTextPostsResponseEdge",
          "cursor": ""
        },
        {
          "node": {
            "thread_items": [
              {
                "post": {
                  "user": {
                    "profile_pic_url": "https://scontent.cdninstagram.com/v/t51.2885-19/358342896_134138973038748_2871278261242540091_n.jpg?stp=dst-jpg_s150x150&_nc_ht=scontent.cdninstagram.com&_nc_cat=100&_nc_ohc=fnBk02x8fYYAX8m4UPS&edm=APs17CUBAAAA&ccb=7-5&oh=00_AfA9CiG3KzCtGkFuFfszkuUxpvtz7Btl_s53wbX5i2ADsw&oe=6531BE5A&_nc_sid=10d13b",
                    "username": "battlenet",
                    "friendship_status": {
                      "following": false,
                      "muting": false,
                      "blocking": null
                    },
                    "pk": "45512948387",
                    "transparency_label": null,
                    "transparency_product": null,
                    "transparency_product_enabled": false,
                    "is_verified": true,
                    "id": null,
                    "text_post_app_is_private": false
                  },
                  "accessibility_caption": "Photo by Battle.net on July 18, 2023. May be a video game screenshot of poster.",
                  "image_versions2": {
                    "candidates": [
                      {
                        "height": 570,
                        "url": "https://scontent.cdninstagram.com/v/t51.2885-15/361552410_2028047794229466_997206794890357915_n.jpg?stp=dst-jpg_e35&efg=eyJ2ZW5jb2RlX3RhZyI6ImltYWdlX3VybGdlbi4xMDE2eDU3MC5zZHIifQ&_nc_ht=scontent.cdninstagram.com&_nc_cat=106&_nc_ohc=nFzR_uuXPc4AX-pizew&edm=APs17CUBAAAA&ccb=7-5&ig_cache_key=MzE0OTkxMDYyMTM2NjYyNjE5MA%3D%3D.2-ccb7-5&oh=00_AfA95Cis8iq14zKslF7q_h1tPjTDkfMjWD9t-A_4GIT3Nw&oe=6530E1FA&_nc_sid=10d13b",
                        "width": 1016
                      },
                      {
                        "height": 404,
                        "url": "https://scontent.cdninstagram.com/v/t51.2885-15/361552410_2028047794229466_997206794890357915_n.jpg?stp=dst-jpg_e35_s720x720&efg=eyJ2ZW5jb2RlX3RhZyI6ImltYWdlX3VybGdlbi4xMDE2eDU3MC5zZHIifQ&_nc_ht=scontent.cdninstagram.com&_nc_cat=106&_nc_ohc=nFzR_uuXPc4AX-pizew&edm=APs17CUBAAAA&ccb=7-5&ig_cache_key=MzE0OTkxMDYyMTM2NjYyNjE5MA%3D%3D.2-ccb7-5&oh=00_AfCtiIytZJAMeIDppYHE69GEKiObTKsPAE4gTGNtGFYkCg&oe=6530E1FA&_nc_sid=10d13b",
                        "width": 720
                      },
                      {
                        "height": 359,
                        "url": "https://scontent.cdninstagram.com/v/t51.2885-15/361552410_2028047794229466_997206794890357915_n.jpg?stp=dst-jpg_e35_s640x640_sh0.08&efg=eyJ2ZW5jb2RlX3RhZyI6ImltYWdlX3VybGdlbi4xMDE2eDU3MC5zZHIifQ&_nc_ht=scontent.cdninstagram.com&_nc_cat=106&_nc_ohc=nFzR_uuXPc4AX-pizew&edm=APs17CUBAAAA&ccb=7-5&ig_cache_key=MzE0OTkxMDYyMTM2NjYyNjE5MA%3D%3D.2-ccb7-5&oh=00_AfBf-LG66-xuyoIjFGvB3J5wzT91RvH1ZWnuD-mQaMot0A&oe=6530E1FA&_nc_sid=10d13b",
                        "width": 640
                      },
                      {
                        "height": 269,
                        "url": "https://scontent.cdninstagram.com/v/t51.2885-15/361552410_2028047794229466_997206794890357915_n.jpg?stp=dst-jpg_e35_s480x480&efg=eyJ2ZW5jb2RlX3RhZyI6ImltYWdlX3VybGdlbi4xMDE2eDU3MC5zZHIifQ&_nc_ht=scontent.cdninstagram.com&_nc_cat=106&_nc_ohc=nFzR_uuXPc4AX-pizew&edm=APs17CUBAAAA&ccb=7-5&ig_cache_key=MzE0OTkxMDYyMTM2NjYyNjE5MA%3D%3D.2-ccb7-5&oh=00_AfARvorHrW8wdt8lcCKc2IWM2v4J9LIcdsG-DdWLZIgbsg&oe=6530E1FA&_nc_sid=10d13b",
                        "width": 480
                      },
                      {
                        "height": 180,
                        "url": "https://scontent.cdninstagram.com/v/t51.2885-15/361552410_2028047794229466_997206794890357915_n.jpg?stp=dst-jpg_e35_s320x320&efg=eyJ2ZW5jb2RlX3RhZyI6ImltYWdlX3VybGdlbi4xMDE2eDU3MC5zZHIifQ&_nc_ht=scontent.cdninstagram.com&_nc_cat=106&_nc_ohc=nFzR_uuXPc4AX-pizew&edm=APs17CUBAAAA&ccb=7-5&ig_cache_key=MzE0OTkxMDYyMTM2NjYyNjE5MA%3D%3D.2-ccb7-5&oh=00_AfAztBgPlkgBTXFNhWzZ_4nfRKN4z3xHoyD7gfEFxmgREg&oe=6530E1FA&_nc_sid=10d13b",
                        "width": 320
                      },
                      {
                        "height": 135,
                        "url": "https://scontent.cdninstagram.com/v/t51.2885-15/361552410_2028047794229466_997206794890357915_n.jpg?stp=dst-jpg_e35_s240x240&efg=eyJ2ZW5jb2RlX3RhZyI6ImltYWdlX3VybGdlbi4xMDE2eDU3MC5zZHIifQ&_nc_ht=scontent.cdninstagram.com&_nc_cat=106&_nc_ohc=nFzR_uuXPc4AX-pizew&edm=APs17CUBAAAA&ccb=7-5&ig_cache_key=MzE0OTkxMDYyMTM2NjYyNjE5MA%3D%3D.2-ccb7-5&oh=00_AfCquFGTrP1WSvipeTDfdbEr0FhU0601sJz7UT5EGBtKWQ&oe=6530E1FA&_nc_sid=10d13b",
                        "width": 240
                      },
                      {
                        "height": 1080,
                        "url": "https://scontent.cdninstagram.com/v/t51.2885-15/361552410_2028047794229466_997206794890357915_n.jpg?stp=c223.0.570.570a_dst-jpg_e35&efg=eyJ2ZW5jb2RlX3RhZyI6ImltYWdlX3VybGdlbi4xMDE2eDU3MC5zZHIifQ&_nc_ht=scontent.cdninstagram.com&_nc_cat=106&_nc_ohc=nFzR_uuXPc4AX-pizew&edm=APs17CUBAAAA&ccb=7-5&ig_cache_key=MzE0OTkxMDYyMTM2NjYyNjE5MA%3D%3D.2-ccb7-5&oh=00_AfBdSt-N8arGSyVgBVTXCAHoaIPDJ5fE6SVr5ha06SJf0A&oe=6530E1FA&_nc_sid=10d13b",
                        "width": 1080
                      },
                      {
                        "height": 750,
                        "url": "https://scontent.cdninstagram.com/v/t51.2885-15/361552410_2028047794229466_997206794890357915_n.jpg?stp=c223.0.570.570a_dst-jpg_e35_s750x750_sh0.08&efg=eyJ2ZW5jb2RlX3RhZyI6ImltYWdlX3VybGdlbi4xMDE2eDU3MC5zZHIifQ&_nc_ht=scontent.cdninstagram.com&_nc_cat=106&_nc_ohc=nFzR_uuXPc4AX-pizew&edm=APs17CUBAAAA&ccb=7-5&ig_cache_key=MzE0OTkxMDYyMTM2NjYyNjE5MA%3D%3D.2-ccb7-5&oh=00_AfBESTRMKB2sRce7Rv_puLmb98T1HTKSnx7iYPygJ9G-Dg&oe=6530E1FA&_nc_sid=10d13b",
                        "width": 750
                      },
                      {
                        "height": 640,
                        "url": "https://scontent.cdninstagram.com/v/t51.2885-15/361552410_2028047794229466_997206794890357915_n.jpg?stp=c223.0.570.570a_dst-jpg_e35_s640x640_sh0.08&efg=eyJ2ZW5jb2RlX3RhZyI6ImltYWdlX3VybGdlbi4xMDE2eDU3MC5zZHIifQ&_nc_ht=scontent.cdninstagram.com&_nc_cat=106&_nc_ohc=nFzR_uuXPc4AX-pizew&edm=APs17CUBAAAA&ccb=7-5&ig_cache_key=MzE0OTkxMDYyMTM2NjYyNjE5MA%3D%3D.2-ccb7-5&oh=00_AfC45zv3dcvBYwIgtUAzG2FS8z8pjuSNTkqd56Fjz520oA&oe=6530E1FA&_nc_sid=10d13b",
                        "width": 640
                      },
                      {
                        "height": 480,
                        "url": "https://scontent.cdninstagram.com/v/t51.2885-15/361552410_2028047794229466_997206794890357915_n.jpg?stp=c223.0.570.570a_dst-jpg_e35_s480x480&efg=eyJ2ZW5jb2RlX3RhZyI6ImltYWdlX3VybGdlbi4xMDE2eDU3MC5zZHIifQ&_nc_ht=scontent.cdninstagram.com&_nc_cat=106&_nc_ohc=nFzR_uuXPc4AX-pizew&edm=APs17CUBAAAA&ccb=7-5&ig_cache_key=MzE0OTkxMDYyMTM2NjYyNjE5MA%3D%3D.2-ccb7-5&oh=00_AfDx9VRIjJYS4PgdlgZtVm_H_OthaHBtgSaTzdp-QdpeVQ&oe=6530E1FA&_nc_sid=10d13b",
                        "width": 480
                      },
                      {
                        "height": 320,
                        "url": "https://scontent.cdninstagram.com/v/t51.2885-15/361552410_2028047794229466_997206794890357915_n.jpg?stp=c223.0.570.570a_dst-jpg_e35_s320x320&efg=eyJ2ZW5jb2RlX3RhZyI6ImltYWdlX3VybGdlbi4xMDE2eDU3MC5zZHIifQ&_nc_ht=scontent.cdninstagram.com&_nc_cat=106&_nc_ohc=nFzR_uuXPc4AX-pizew&edm=APs17CUBAAAA&ccb=7-5&ig_cache_key=MzE0OTkxMDYyMTM2NjYyNjE5MA%3D%3D.2-ccb7-5&oh=00_AfArjrYstjOZMi7hX5Mi7w44nAUzSSxcFX7xMHRwV8PcSw&oe=6530E1FA&_nc_sid=10d13b",
                        "width": 320
                      },
                      {
                        "height": 240,
                        "url": "https://scontent.cdninstagram.com/v/t51.2885-15/361552410_2028047794229466_997206794890357915_n.jpg?stp=c223.0.570.570a_dst-jpg_e35_s240x240&efg=eyJ2ZW5jb2RlX3RhZyI6ImltYWdlX3VybGdlbi4xMDE2eDU3MC5zZHIifQ&_nc_ht=scontent.cdninstagram.com&_nc_cat=106&_nc_ohc=nFzR_uuXPc4AX-pizew&edm=APs17CUBAAAA&ccb=7-5&ig_cache_key=MzE0OTkxMDYyMTM2NjYyNjE5MA%3D%3D.2-ccb7-5&oh=00_AfBebMbcoHeEhTKjFNWUTr4QjI98Pkv-4mRuJJAanrpbBg&oe=6530E1FA&_nc_sid=10d13b",
                        "width": 240
                      },
                      {
                        "height": 150,
                        "url": "https://scontent.cdninstagram.com/v/t51.2885-15/361552410_2028047794229466_997206794890357915_n.jpg?stp=c223.0.570.570a_dst-jpg_e35_s150x150&efg=eyJ2ZW5jb2RlX3RhZyI6ImltYWdlX3VybGdlbi4xMDE2eDU3MC5zZHIifQ&_nc_ht=scontent.cdninstagram.com&_nc_cat=106&_nc_ohc=nFzR_uuXPc4AX-pizew&edm=APs17CUBAAAA&ccb=7-5&ig_cache_key=MzE0OTkxMDYyMTM2NjYyNjE5MA%3D%3D.2-ccb7-5&oh=00_AfAJTzpGofrIIbRXtNMOS-52RGXcnQzZU6qPaTGqlLy9zA&oe=6530E1FA&_nc_sid=10d13b",
                        "width": 150
                      }
                    ]
                  },
                  "original_width": 1016,
                  "original_height": 570,
                  "code": "Cu2uwVsyaeO",
                  "video_versions": null,
                  "carousel_media": null,
                  "pk": "3149910621366626190",
                  "text_post_app_info": {
                    "share_info": {
                      "can_quote_post": true,
                      "can_repost": true,
                      "is_reposted_by_viewer": false,
                      "repost_restricted_reason": null,
                      "__typename": "XDTShareInfo",
                      "reposted_post": null,
                      "quoted_post": null
                    },
                    "can_reply": true,
                    "is_reply": false,
                    "hush_info": null,
                    "reply_control": "everyone",
                    "pinned_post_info": null,
                    "link_preview_attachment": null,
                    "reply_to_author": null,
                    "is_post_unavailable": false,
                    "post_unavailable_reason": null
                  },
                  "is_fb_only": null,
                  "is_internal_only": null,
                  "id": "3149910621366626190_45512948387",
                  "media_type": 1,
                  "has_audio": null,
                  "audio": null,
                  "transcription_data": null,
                  "caption_is_edited": false,
                  "has_liked": false,
                  "is_paid_partnership": null,
                  "like_and_view_counts_disabled": false,
                  "taken_at": 1689718629,
                  "caption": {
                    "text": "DiabloIV Season of the Malignant begins in only 2 days!\n\nAre you ready to face the corruption that infects Sanctuary?"
                  },
                  "like_count": 71,
                  "media_overlay_info": null
                },
                "line_type": "line",
                "view_replies_cta_string": "3 respuestas",
                "reply_facepile_users": [
                  {
                    "__typename": "XDTUserDict",
                    "id": null,
                    "profile_pic_url": "https://scontent.cdninstagram.com/v/t51.2885-19/358226001_637574461631799_8816362583206676091_n.jpg?stp=dst-jpg_s150x150&_nc_ht=scontent.cdninstagram.com&_nc_cat=103&_nc_ohc=pZi0jrutlioAX9y7hfH&edm=APs17CUBAAAA&ccb=7-5&oh=00_AfA4uKMRSJEerkKa5EPhMM2DFr3oc8nrVEX7Wz4vovqjSA&oe=65318B6F&_nc_sid=10d13b"
                  },
                  {
                    "__typename": "XDTUserDict",
                    "id": null,
                    "profile_pic_url": "https://scontent.cdninstagram.com/v/t51.2885-19/358379314_645193867643598_7113731897239711402_n.jpg?stp=dst-jpg_s150x150&_nc_ht=scontent.cdninstagram.com&_nc_cat=106&_nc_ohc=lhvVDoARtnEAX-2ncai&edm=APs17CUBAAAA&ccb=7-5&oh=00_AfAZbUbToFnBUiEA02n_7L1Wud1sD5hsiaD62LtJXLZiQg&oe=6531DCDF&_nc_sid=10d13b"
                  }
                ],
                "should_show_replies_cta": true,
                "__typename": "XDTThreadItem"
              }
            ],
            "id": "3149910621366626190",
            "__typename": "XDTThread"
          },
          "__typename": "XDTUserTextPostsResponseEdge",
          "cursor": ""
        },
        {
          "node": {
            "thread_items": [
              {
                "post": {
                  "user": {
                    "profile_pic_url": "https://scontent.cdninstagram.com/v/t51.2885-19/358342896_134138973038748_2871278261242540091_n.jpg?stp=dst-jpg_s150x150&_nc_ht=scontent.cdninstagram.com&_nc_cat=100&_nc_ohc=fnBk02x8fYYAX8m4UPS&edm=APs17CUBAAAA&ccb=7-5&oh=00_AfA9CiG3KzCtGkFuFfszkuUxpvtz7Btl_s53wbX5i2ADsw&oe=6531BE5A&_nc_sid=10d13b",
                    "username": "battlenet",
                    "friendship_status": {
                      "following": false,
                      "muting": false,
                      "blocking": null
                    },
                    "pk": "45512948387",
                    "transparency_label": null,
                    "transparency_product": null,
                    "transparency_product_enabled": false,
                    "is_verified": true,
                    "id": null,
                    "text_post_app_is_private": false
                  },
                  "accessibility_caption": "Photo by Battle.net on July 14, 2023.",
                  "image_versions2": {
                    "candidates": [
                      {
                        "height": 1080,
                        "url": "https://scontent.cdninstagram.com/v/t51.2885-15/360002142_595187949464300_5454822872245033586_n.jpg?stp=dst-jpg_e35&efg=eyJ2ZW5jb2RlX3RhZyI6ImltYWdlX3VybGdlbi4xOTIweDEwODAuc2RyIn0&_nc_ht=scontent.cdninstagram.com&_nc_cat=108&_nc_ohc=weGCjPUR7DQAX80Gmu6&edm=APs17CUBAAAA&ccb=7-5&ig_cache_key=MzE0Njg1MDc0OTQyNzEzNTI4Ng%3D%3D.2-ccb7-5&oh=00_AfChPj7G9kPiw4BTznQChfbXdlu22v_QChYU2lSNNEyeZg&oe=653075AE&_nc_sid=10d13b",
                        "width": 1920
                      },
                      {
                        "height": 608,
                        "url": "https://scontent.cdninstagram.com/v/t51.2885-15/360002142_595187949464300_5454822872245033586_n.jpg?stp=dst-jpg_e35_s1080x1080&efg=eyJ2ZW5jb2RlX3RhZyI6ImltYWdlX3VybGdlbi4xOTIweDEwODAuc2RyIn0&_nc_ht=scontent.cdninstagram.com&_nc_cat=108&_nc_ohc=weGCjPUR7DQAX80Gmu6&edm=APs17CUBAAAA&ccb=7-5&ig_cache_key=MzE0Njg1MDc0OTQyNzEzNTI4Ng%3D%3D.2-ccb7-5&oh=00_AfB0ZSOlTjZSdLahPZzKHbGsSBmCFa51GLIlAcfQY3eTWw&oe=653075AE&_nc_sid=10d13b",
                        "width": 1080
                      },
                      {
                        "height": 405,
                        "url": "https://scontent.cdninstagram.com/v/t51.2885-15/360002142_595187949464300_5454822872245033586_n.jpg?stp=dst-jpg_e35_s720x720&efg=eyJ2ZW5jb2RlX3RhZyI6ImltYWdlX3VybGdlbi4xOTIweDEwODAuc2RyIn0&_nc_ht=scontent.cdninstagram.com&_nc_cat=108&_nc_ohc=weGCjPUR7DQAX80Gmu6&edm=APs17CUBAAAA&ccb=7-5&ig_cache_key=MzE0Njg1MDc0OTQyNzEzNTI4Ng%3D%3D.2-ccb7-5&oh=00_AfAhRnO_fNh8Zv1MQ2c-Vip8_ZM7ex4hJp74ArmKojzxfA&oe=653075AE&_nc_sid=10d13b",
                        "width": 720
                      },
                      {
                        "height": 360,
                        "url": "https://scontent.cdninstagram.com/v/t51.2885-15/360002142_595187949464300_5454822872245033586_n.jpg?stp=dst-jpg_e35_s640x640_sh0.08&efg=eyJ2ZW5jb2RlX3RhZyI6ImltYWdlX3VybGdlbi4xOTIweDEwODAuc2RyIn0&_nc_ht=scontent.cdninstagram.com&_nc_cat=108&_nc_ohc=weGCjPUR7DQAX80Gmu6&edm=APs17CUBAAAA&ccb=7-5&ig_cache_key=MzE0Njg1MDc0OTQyNzEzNTI4Ng%3D%3D.2-ccb7-5&oh=00_AfAy9CQbQ2hB94r5_Yis9-PNJAmuFscrdO9m4mTSuMxi5w&oe=653075AE&_nc_sid=10d13b",
                        "width": 640
                      },
                      {
                        "height": 270,
                        "url": "https://scontent.cdninstagram.com/v/t51.2885-15/360002142_595187949464300_5454822872245033586_n.jpg?stp=dst-jpg_e35_s480x480&efg=eyJ2ZW5jb2RlX3RhZyI6ImltYWdlX3VybGdlbi4xOTIweDEwODAuc2RyIn0&_nc_ht=scontent.cdninstagram.com&_nc_cat=108&_nc_ohc=weGCjPUR7DQAX80Gmu6&edm=APs17CUBAAAA&ccb=7-5&ig_cache_key=MzE0Njg1MDc0OTQyNzEzNTI4Ng%3D%3D.2-ccb7-5&oh=00_AfCZ7aOTVm5SvF2vosDi6Vf7wVhI3WbViYAX1ANnJ3g3Rw&oe=653075AE&_nc_sid=10d13b",
                        "width": 480
                      },
                      {
                        "height": 180,
                        "url": "https://scontent.cdninstagram.com/v/t51.2885-15/360002142_595187949464300_5454822872245033586_n.jpg?stp=dst-jpg_e35_s320x320&efg=eyJ2ZW5jb2RlX3RhZyI6ImltYWdlX3VybGdlbi4xOTIweDEwODAuc2RyIn0&_nc_ht=scontent.cdninstagram.com&_nc_cat=108&_nc_ohc=weGCjPUR7DQAX80Gmu6&edm=APs17CUBAAAA&ccb=7-5&ig_cache_key=MzE0Njg1MDc0OTQyNzEzNTI4Ng%3D%3D.2-ccb7-5&oh=00_AfAadUBj1E5uyHxSwGSWuGd7e6DoIX9S_vPVALegwngV9A&oe=653075AE&_nc_sid=10d13b",
                        "width": 320
                      },
                      {
                        "height": 135,
                        "url": "https://scontent.cdninstagram.com/v/t51.2885-15/360002142_595187949464300_5454822872245033586_n.jpg?stp=dst-jpg_e35_s240x240&efg=eyJ2ZW5jb2RlX3RhZyI6ImltYWdlX3VybGdlbi4xOTIweDEwODAuc2RyIn0&_nc_ht=scontent.cdninstagram.com&_nc_cat=108&_nc_ohc=weGCjPUR7DQAX80Gmu6&edm=APs17CUBAAAA&ccb=7-5&ig_cache_key=MzE0Njg1MDc0OTQyNzEzNTI4Ng%3D%3D.2-ccb7-5&oh=00_AfACNOAERre5Y9rpMb-BuvPJrn67bVl8zilG6LhgCAzlbg&oe=653075AE&_nc_sid=10d13b",
                        "width": 240
                      },
                      {
                        "height": 1080,
                        "url": "https://scontent.cdninstagram.com/v/t51.2885-15/360002142_595187949464300_5454822872245033586_n.jpg?stp=c420.0.1080.1080a_dst-jpg_e35_s1080x1080&efg=eyJ2ZW5jb2RlX3RhZyI6ImltYWdlX3VybGdlbi4xOTIweDEwODAuc2RyIn0&_nc_ht=scontent.cdninstagram.com&_nc_cat=108&_nc_ohc=weGCjPUR7DQAX80Gmu6&edm=APs17CUBAAAA&ccb=7-5&ig_cache_key=MzE0Njg1MDc0OTQyNzEzNTI4Ng%3D%3D.2-ccb7-5&oh=00_AfBTJnUfM0nmqC73xwKfsG_DO5DZRVsVfM4QGa788bq6uw&oe=653075AE&_nc_sid=10d13b",
                        "width": 1080
                      },
                      {
                        "height": 750,
                        "url": "https://scontent.cdninstagram.com/v/t51.2885-15/360002142_595187949464300_5454822872245033586_n.jpg?stp=c420.0.1080.1080a_dst-jpg_e35_s750x750_sh0.08&efg=eyJ2ZW5jb2RlX3RhZyI6ImltYWdlX3VybGdlbi4xOTIweDEwODAuc2RyIn0&_nc_ht=scontent.cdninstagram.com&_nc_cat=108&_nc_ohc=weGCjPUR7DQAX80Gmu6&edm=APs17CUBAAAA&ccb=7-5&ig_cache_key=MzE0Njg1MDc0OTQyNzEzNTI4Ng%3D%3D.2-ccb7-5&oh=00_AfAIMNPp7arRDxEvfRe40-8Or4pcYAWix6O27fzU6jYeaA&oe=653075AE&_nc_sid=10d13b",
                        "width": 750
                      },
                      {
                        "height": 640,
                        "url": "https://scontent.cdninstagram.com/v/t51.2885-15/360002142_595187949464300_5454822872245033586_n.jpg?stp=c420.0.1080.1080a_dst-jpg_e35_s640x640_sh0.08&efg=eyJ2ZW5jb2RlX3RhZyI6ImltYWdlX3VybGdlbi4xOTIweDEwODAuc2RyIn0&_nc_ht=scontent.cdninstagram.com&_nc_cat=108&_nc_ohc=weGCjPUR7DQAX80Gmu6&edm=APs17CUBAAAA&ccb=7-5&ig_cache_key=MzE0Njg1MDc0OTQyNzEzNTI4Ng%3D%3D.2-ccb7-5&oh=00_AfDJxricC6pvVm0D_457SI3lGWqroSDzfAklVhtQE0TTbg&oe=653075AE&_nc_sid=10d13b",
                        "width": 640
                      },
                      {
                        "height": 480,
                        "url": "https://scontent.cdninstagram.com/v/t51.2885-15/360002142_595187949464300_5454822872245033586_n.jpg?stp=c420.0.1080.1080a_dst-jpg_e35_s480x480&efg=eyJ2ZW5jb2RlX3RhZyI6ImltYWdlX3VybGdlbi4xOTIweDEwODAuc2RyIn0&_nc_ht=scontent.cdninstagram.com&_nc_cat=108&_nc_ohc=weGCjPUR7DQAX80Gmu6&edm=APs17CUBAAAA&ccb=7-5&ig_cache_key=MzE0Njg1MDc0OTQyNzEzNTI4Ng%3D%3D.2-ccb7-5&oh=00_AfA2DTz14if29N7BNo3WzcVB2881Aof0fXaXRWJOKS7OAw&oe=653075AE&_nc_sid=10d13b",
                        "width": 480
                      },
                      {
                        "height": 320,
                        "url": "https://scontent.cdninstagram.com/v/t51.2885-15/360002142_595187949464300_5454822872245033586_n.jpg?stp=c420.0.1080.1080a_dst-jpg_e35_s320x320&efg=eyJ2ZW5jb2RlX3RhZyI6ImltYWdlX3VybGdlbi4xOTIweDEwODAuc2RyIn0&_nc_ht=scontent.cdninstagram.com&_nc_cat=108&_nc_ohc=weGCjPUR7DQAX80Gmu6&edm=APs17CUBAAAA&ccb=7-5&ig_cache_key=MzE0Njg1MDc0OTQyNzEzNTI4Ng%3D%3D.2-ccb7-5&oh=00_AfCRzqwLzTaLedmcnwXxSGDU4Bx3z0BqETzHG8xDHu719A&oe=653075AE&_nc_sid=10d13b",
                        "width": 320
                      },
                      {
                        "height": 240,
                        "url": "https://scontent.cdninstagram.com/v/t51.2885-15/360002142_595187949464300_5454822872245033586_n.jpg?stp=c420.0.1080.1080a_dst-jpg_e35_s240x240&efg=eyJ2ZW5jb2RlX3RhZyI6ImltYWdlX3VybGdlbi4xOTIweDEwODAuc2RyIn0&_nc_ht=scontent.cdninstagram.com&_nc_cat=108&_nc_ohc=weGCjPUR7DQAX80Gmu6&edm=APs17CUBAAAA&ccb=7-5&ig_cache_key=MzE0Njg1MDc0OTQyNzEzNTI4Ng%3D%3D.2-ccb7-5&oh=00_AfCUwhclXl_-2KjiHSnjtLMmzkGhICKVKaieXBxAGuZSKA&oe=653075AE&_nc_sid=10d13b",
                        "width": 240
                      },
                      {
                        "height": 150,
                        "url": "https://scontent.cdninstagram.com/v/t51.2885-15/360002142_595187949464300_5454822872245033586_n.jpg?stp=c420.0.1080.1080a_dst-jpg_e35_s150x150&efg=eyJ2ZW5jb2RlX3RhZyI6ImltYWdlX3VybGdlbi4xOTIweDEwODAuc2RyIn0&_nc_ht=scontent.cdninstagram.com&_nc_cat=108&_nc_ohc=weGCjPUR7DQAX80Gmu6&edm=APs17CUBAAAA&ccb=7-5&ig_cache_key=MzE0Njg1MDc0OTQyNzEzNTI4Ng%3D%3D.2-ccb7-5&oh=00_AfCoWQHkssPfa6C96wncewT15cGGxyQ8Gcpze781RT5z2A&oe=653075AE&_nc_sid=10d13b",
                        "width": 150
                      }
                    ]
                  },
                  "original_width": 1920,
                  "original_height": 1080,
                  "code": "Cur3BV4xrM2",
                  "video_versions": null,
                  "carousel_media": null,
                  "pk": "3146850749427135286",
                  "text_post_app_info": {
                    "share_info": {
                      "can_quote_post": true,
                      "can_repost": true,
                      "is_reposted_by_viewer": false,
                      "repost_restricted_reason": null,
                      "__typename": "XDTShareInfo",
                      "reposted_post": null,
                      "quoted_post": null
                    },
                    "can_reply": true,
                    "is_reply": false,
                    "hush_info": null,
                    "reply_control": "everyone",
                    "pinned_post_info": null,
                    "link_preview_attachment": null,
                    "reply_to_author": null,
                    "is_post_unavailable": false,
                    "post_unavailable_reason": null
                  },
                  "is_fb_only": null,
                  "is_internal_only": null,
                  "id": "3146850749427135286_45512948387",
                  "media_type": 1,
                  "has_audio": null,
                  "audio": null,
                  "transcription_data": null,
                  "caption_is_edited": false,
                  "has_liked": false,
                  "is_paid_partnership": null,
                  "like_and_view_counts_disabled": false,
                  "taken_at": 1689353863,
                  "caption": {
                    "text": "There are so MANY WHELPS at the Little Scales Daycare to watch over, but we're sure everyone can HANDLE IT."
                  },
                  "like_count": 56,
                  "media_overlay_info": null
                },
                "line_type": "line",
                "view_replies_cta_string": "1 respuesta",
                "reply_facepile_users": [
                  {
                    "__typename": "XDTUserDict",
                    "id": null,
                    "profile_pic_url": "https://scontent.cdninstagram.com/v/t51.2885-19/358031575_288804367042465_7084277961680858655_n.jpg?stp=dst-jpg_s150x150&_nc_ht=scontent.cdninstagram.com&_nc_cat=101&_nc_ohc=7uZjguiqDe8AX-qzPuw&edm=APs17CUBAAAA&ccb=7-5&oh=00_AfBr4UGFTntD3K6Uc9pPTosnBhBY0OUtX8hszgnUlZ6gtw&oe=65322057&_nc_sid=10d13b"
                  }
                ],
                "should_show_replies_cta": true,
                "__typename": "XDTThreadItem"
              }
            ],
            "id": "3146850749427135286",
            "__typename": "XDTThread"
          },
          "__typename": "XDTUserTextPostsResponseEdge",
          "cursor": ""
        },
        {
          "node": {
            "thread_items": [
              {
                "post": {
                  "user": {
                    "profile_pic_url": "https://scontent.cdninstagram.com/v/t51.2885-19/358342896_134138973038748_2871278261242540091_n.jpg?stp=dst-jpg_s150x150&_nc_ht=scontent.cdninstagram.com&_nc_cat=100&_nc_ohc=fnBk02x8fYYAX8m4UPS&edm=APs17CUBAAAA&ccb=7-5&oh=00_AfA9CiG3KzCtGkFuFfszkuUxpvtz7Btl_s53wbX5i2ADsw&oe=6531BE5A&_nc_sid=10d13b",
                    "username": "battlenet",
                    "friendship_status": {
                      "following": false,
                      "muting": false,
                      "blocking": null
                    },
                    "pk": "45512948387",
                    "transparency_label": null,
                    "transparency_product": null,
                    "transparency_product_enabled": false,
                    "is_verified": true,
                    "id": null,
                    "text_post_app_is_private": false
                  },
                  "accessibility_caption": "Photo by Battle.net on July 12, 2023.",
                  "image_versions2": {
                    "candidates": [
                      {
                        "height": 1080,
                        "url": "https://scontent.cdninstagram.com/v/t51.2885-15/359412865_6263750376994426_6476948640066139316_n.jpg?stp=dst-jpg_e35&efg=eyJ2ZW5jb2RlX3RhZyI6ImltYWdlX3VybGdlbi4xMDgweDEwODAuc2RyIn0&_nc_ht=scontent.cdninstagram.com&_nc_cat=110&_nc_ohc=80AXD-abYOkAX-jkH-L&edm=APs17CUBAAAA&ccb=7-5&ig_cache_key=MzE0NTQwMjQ5ODYxMDAzNTgzOQ%3D%3D.2-ccb7-5&oh=00_AfAgQGxbn2jOdhla7m_Q5eHqPrcKandlIvce8gycBQ01IQ&oe=6530C897&_nc_sid=10d13b",
                        "width": 1080
                      },
                      {
                        "height": 720,
                        "url": "https://scontent.cdninstagram.com/v/t51.2885-15/359412865_6263750376994426_6476948640066139316_n.jpg?stp=dst-jpg_e35_s720x720&efg=eyJ2ZW5jb2RlX3RhZyI6ImltYWdlX3VybGdlbi4xMDgweDEwODAuc2RyIn0&_nc_ht=scontent.cdninstagram.com&_nc_cat=110&_nc_ohc=80AXD-abYOkAX-jkH-L&edm=APs17CUBAAAA&ccb=7-5&ig_cache_key=MzE0NTQwMjQ5ODYxMDAzNTgzOQ%3D%3D.2-ccb7-5&oh=00_AfCNckYLX4w1sDhyUgTv8XgUDjcH6ncsXgeaEkBbsjK_Pw&oe=6530C897&_nc_sid=10d13b",
                        "width": 720
                      },
                      {
                        "height": 640,
                        "url": "https://scontent.cdninstagram.com/v/t51.2885-15/359412865_6263750376994426_6476948640066139316_n.jpg?stp=dst-jpg_e35_s640x640_sh0.08&efg=eyJ2ZW5jb2RlX3RhZyI6ImltYWdlX3VybGdlbi4xMDgweDEwODAuc2RyIn0&_nc_ht=scontent.cdninstagram.com&_nc_cat=110&_nc_ohc=80AXD-abYOkAX-jkH-L&edm=APs17CUBAAAA&ccb=7-5&ig_cache_key=MzE0NTQwMjQ5ODYxMDAzNTgzOQ%3D%3D.2-ccb7-5&oh=00_AfB71k8XUfKP4j2YMfhhB1AWegn-5xcRP5wEFu1C-9wU5Q&oe=6530C897&_nc_sid=10d13b",
                        "width": 640
                      },
                      {
                        "height": 480,
                        "url": "https://scontent.cdninstagram.com/v/t51.2885-15/359412865_6263750376994426_6476948640066139316_n.jpg?stp=dst-jpg_e35_s480x480&efg=eyJ2ZW5jb2RlX3RhZyI6ImltYWdlX3VybGdlbi4xMDgweDEwODAuc2RyIn0&_nc_ht=scontent.cdninstagram.com&_nc_cat=110&_nc_ohc=80AXD-abYOkAX-jkH-L&edm=APs17CUBAAAA&ccb=7-5&ig_cache_key=MzE0NTQwMjQ5ODYxMDAzNTgzOQ%3D%3D.2-ccb7-5&oh=00_AfBSytlUB9a2PNjquseeJPHaINlsbZJLxT0sGBQBOe6VZQ&oe=6530C897&_nc_sid=10d13b",
                        "width": 480
                      },
                      {
                        "height": 320,
                        "url": "https://scontent.cdninstagram.com/v/t51.2885-15/359412865_6263750376994426_6476948640066139316_n.jpg?stp=dst-jpg_e35_s320x320&efg=eyJ2ZW5jb2RlX3RhZyI6ImltYWdlX3VybGdlbi4xMDgweDEwODAuc2RyIn0&_nc_ht=scontent.cdninstagram.com&_nc_cat=110&_nc_ohc=80AXD-abYOkAX-jkH-L&edm=APs17CUBAAAA&ccb=7-5&ig_cache_key=MzE0NTQwMjQ5ODYxMDAzNTgzOQ%3D%3D.2-ccb7-5&oh=00_AfCgZwaKVH9bVlNyY3tj0NGagYjglSSteYIG8WojGNt-Yw&oe=6530C897&_nc_sid=10d13b",
                        "width": 320
                      },
                      {
                        "height": 240,
                        "url": "https://scontent.cdninstagram.com/v/t51.2885-15/359412865_6263750376994426_6476948640066139316_n.jpg?stp=dst-jpg_e35_s240x240&efg=eyJ2ZW5jb2RlX3RhZyI6ImltYWdlX3VybGdlbi4xMDgweDEwODAuc2RyIn0&_nc_ht=scontent.cdninstagram.com&_nc_cat=110&_nc_ohc=80AXD-abYOkAX-jkH-L&edm=APs17CUBAAAA&ccb=7-5&ig_cache_key=MzE0NTQwMjQ5ODYxMDAzNTgzOQ%3D%3D.2-ccb7-5&oh=00_AfCyxaQ5h85b5zVoDnmax0X3LE0eq1H9roaSHeaDL4ys3g&oe=6530C897&_nc_sid=10d13b",
                        "width": 240
                      },
                      {
                        "height": 1080,
                        "url": "https://scontent.cdninstagram.com/v/t51.2885-15/359412865_6263750376994426_6476948640066139316_n.jpg?stp=dst-jpg_e35&efg=eyJ2ZW5jb2RlX3RhZyI6ImltYWdlX3VybGdlbi4xMDgweDEwODAuc2RyIn0&_nc_ht=scontent.cdninstagram.com&_nc_cat=110&_nc_ohc=80AXD-abYOkAX-jkH-L&edm=APs17CUBAAAA&ccb=7-5&ig_cache_key=MzE0NTQwMjQ5ODYxMDAzNTgzOQ%3D%3D.2-ccb7-5&oh=00_AfAgQGxbn2jOdhla7m_Q5eHqPrcKandlIvce8gycBQ01IQ&oe=6530C897&_nc_sid=10d13b",
                        "width": 1080
                      },
                      {
                        "height": 750,
                        "url": "https://scontent.cdninstagram.com/v/t51.2885-15/359412865_6263750376994426_6476948640066139316_n.jpg?stp=dst-jpg_e35_s750x750_sh0.08&efg=eyJ2ZW5jb2RlX3RhZyI6ImltYWdlX3VybGdlbi4xMDgweDEwODAuc2RyIn0&_nc_ht=scontent.cdninstagram.com&_nc_cat=110&_nc_ohc=80AXD-abYOkAX-jkH-L&edm=APs17CUBAAAA&ccb=7-5&ig_cache_key=MzE0NTQwMjQ5ODYxMDAzNTgzOQ%3D%3D.2-ccb7-5&oh=00_AfB_tFSIsy5kQvph6hHKCz-BFlZWLzXwfvjDSCxjJs48sA&oe=6530C897&_nc_sid=10d13b",
                        "width": 750
                      },
                      {
                        "height": 640,
                        "url": "https://scontent.cdninstagram.com/v/t51.2885-15/359412865_6263750376994426_6476948640066139316_n.jpg?stp=dst-jpg_e35_s640x640_sh0.08&efg=eyJ2ZW5jb2RlX3RhZyI6ImltYWdlX3VybGdlbi4xMDgweDEwODAuc2RyIn0&_nc_ht=scontent.cdninstagram.com&_nc_cat=110&_nc_ohc=80AXD-abYOkAX-jkH-L&edm=APs17CUBAAAA&ccb=7-5&ig_cache_key=MzE0NTQwMjQ5ODYxMDAzNTgzOQ%3D%3D.2-ccb7-5&oh=00_AfB71k8XUfKP4j2YMfhhB1AWegn-5xcRP5wEFu1C-9wU5Q&oe=6530C897&_nc_sid=10d13b",
                        "width": 640
                      },
                      {
                        "height": 480,
                        "url": "https://scontent.cdninstagram.com/v/t51.2885-15/359412865_6263750376994426_6476948640066139316_n.jpg?stp=dst-jpg_e35_s480x480&efg=eyJ2ZW5jb2RlX3RhZyI6ImltYWdlX3VybGdlbi4xMDgweDEwODAuc2RyIn0&_nc_ht=scontent.cdninstagram.com&_nc_cat=110&_nc_ohc=80AXD-abYOkAX-jkH-L&edm=APs17CUBAAAA&ccb=7-5&ig_cache_key=MzE0NTQwMjQ5ODYxMDAzNTgzOQ%3D%3D.2-ccb7-5&oh=00_AfBSytlUB9a2PNjquseeJPHaINlsbZJLxT0sGBQBOe6VZQ&oe=6530C897&_nc_sid=10d13b",
                        "width": 480
                      },
                      {
                        "height": 320,
                        "url": "https://scontent.cdninstagram.com/v/t51.2885-15/359412865_6263750376994426_6476948640066139316_n.jpg?stp=dst-jpg_e35_s320x320&efg=eyJ2ZW5jb2RlX3RhZyI6ImltYWdlX3VybGdlbi4xMDgweDEwODAuc2RyIn0&_nc_ht=scontent.cdninstagram.com&_nc_cat=110&_nc_ohc=80AXD-abYOkAX-jkH-L&edm=APs17CUBAAAA&ccb=7-5&ig_cache_key=MzE0NTQwMjQ5ODYxMDAzNTgzOQ%3D%3D.2-ccb7-5&oh=00_AfCgZwaKVH9bVlNyY3tj0NGagYjglSSteYIG8WojGNt-Yw&oe=6530C897&_nc_sid=10d13b",
                        "width": 320
                      },
                      {
                        "height": 240,
                        "url": "https://scontent.cdninstagram.com/v/t51.2885-15/359412865_6263750376994426_6476948640066139316_n.jpg?stp=dst-jpg_e35_s240x240&efg=eyJ2ZW5jb2RlX3RhZyI6ImltYWdlX3VybGdlbi4xMDgweDEwODAuc2RyIn0&_nc_ht=scontent.cdninstagram.com&_nc_cat=110&_nc_ohc=80AXD-abYOkAX-jkH-L&edm=APs17CUBAAAA&ccb=7-5&ig_cache_key=MzE0NTQwMjQ5ODYxMDAzNTgzOQ%3D%3D.2-ccb7-5&oh=00_AfCyxaQ5h85b5zVoDnmax0X3LE0eq1H9roaSHeaDL4ys3g&oe=6530C897&_nc_sid=10d13b",
                        "width": 240
                      },
                      {
                        "height": 150,
                        "url": "https://scontent.cdninstagram.com/v/t51.2885-15/359412865_6263750376994426_6476948640066139316_n.jpg?stp=dst-jpg_e35_s150x150&efg=eyJ2ZW5jb2RlX3RhZyI6ImltYWdlX3VybGdlbi4xMDgweDEwODAuc2RyIn0&_nc_ht=scontent.cdninstagram.com&_nc_cat=110&_nc_ohc=80AXD-abYOkAX-jkH-L&edm=APs17CUBAAAA&ccb=7-5&ig_cache_key=MzE0NTQwMjQ5ODYxMDAzNTgzOQ%3D%3D.2-ccb7-5&oh=00_AfD-gQlHhKHAd75ZviWaS7A3xxDiPHHpxXVf0LPf9P6Q_Q&oe=6530C897&_nc_sid=10d13b",
                        "width": 150
                      }
                    ]
                  },
                  "original_width": 1080,
                  "original_height": 1080,
                  "code": "CumtuhNRvx_",
                  "video_versions": null,
                  "carousel_media": null,
                  "pk": "3145402498610035839",
                  "text_post_app_info": {
                    "share_info": {
                      "can_quote_post": true,
                      "can_repost": true,
                      "is_reposted_by_viewer": false,
                      "repost_restricted_reason": null,
                      "__typename": "XDTShareInfo",
                      "reposted_post": null,
                      "quoted_post": null
                    },
                    "can_reply": true,
                    "is_reply": false,
                    "hush_info": null,
                    "reply_control": "everyone",
                    "pinned_post_info": null,
                    "link_preview_attachment": null,
                    "reply_to_author": null,
                    "is_post_unavailable": false,
                    "post_unavailable_reason": null
                  },
                  "is_fb_only": null,
                  "is_internal_only": null,
                  "id": "3145402498610035839_45512948387",
                  "media_type": 1,
                  "has_audio": null,
                  "audio": null,
                  "transcription_data": null,
                  "caption_is_edited": false,
                  "has_liked": false,
                  "is_paid_partnership": null,
                  "like_and_view_counts_disabled": false,
                  "taken_at": 1689181218,
                  "caption": {
                    "text": "Winton"
                  },
                  "like_count": 295,
                  "media_overlay_info": null
                },
                "line_type": "line",
                "view_replies_cta_string": "25 respuestas",
                "reply_facepile_users": [
                  {
                    "__typename": "XDTUserDict",
                    "id": null,
                    "profile_pic_url": "https://scontent.cdninstagram.com/v/t51.2885-19/361317891_973224034001555_7207345014321862977_n.jpg?stp=dst-jpg_s150x150&_nc_ht=scontent.cdninstagram.com&_nc_cat=111&_nc_ohc=oQyae0BW7PUAX-TqSIw&edm=APs17CUBAAAA&ccb=7-5&oh=00_AfBu-nb9cnFUiR1WUM9ZlhbgNjC35geKyxDzLL124C9Q2A&oe=6532BB28&_nc_sid=10d13b"
                  },
                  {
                    "__typename": "XDTUserDict",
                    "id": null,
                    "profile_pic_url": "https://scontent.cdninstagram.com/v/t51.2885-19/359349312_218605217804189_322499762350675680_n.jpg?stp=dst-jpg_s150x150&_nc_ht=scontent.cdninstagram.com&_nc_cat=105&_nc_ohc=13dyadjtGBMAX_UEuz4&edm=APs17CUBAAAA&ccb=7-5&oh=00_AfBEwyYJS1rQV5FdZIydYX8GgWPwAeB0ru0Q7xOzWXf-xw&oe=653318B4&_nc_sid=10d13b"
                  },
                  {
                    "__typename": "XDTUserDict",
                    "id": null,
                    "profile_pic_url": "https://scontent.cdninstagram.com/v/t51.2885-19/358009585_835568428142350_1051898432083056207_n.jpg?stp=dst-jpg_s150x150&_nc_ht=scontent.cdninstagram.com&_nc_cat=110&_nc_ohc=mfA1NFdlFnYAX8Ulkz4&edm=APs17CUBAAAA&ccb=7-5&oh=00_AfDrtw_npOA9sXRY6ggHUGQNDDn5QPmMAwtr61XtyQkEKw&oe=6531A8F3&_nc_sid=10d13b"
                  }
                ],
                "should_show_replies_cta": true,
                "__typename": "XDTThreadItem"
              }
            ],
            "id": "3145402498610035839",
            "__typename": "XDTThread"
          },
          "__typename": "XDTUserTextPostsResponseEdge",
          "cursor": ""
        },
        {
          "node": {
            "thread_items": [
              {
                "post": {
                  "user": {
                    "profile_pic_url": "https://scontent.cdninstagram.com/v/t51.2885-19/358342896_134138973038748_2871278261242540091_n.jpg?stp=dst-jpg_s150x150&_nc_ht=scontent.cdninstagram.com&_nc_cat=100&_nc_ohc=fnBk02x8fYYAX8m4UPS&edm=APs17CUBAAAA&ccb=7-5&oh=00_AfA9CiG3KzCtGkFuFfszkuUxpvtz7Btl_s53wbX5i2ADsw&oe=6531BE5A&_nc_sid=10d13b",
                    "username": "battlenet",
                    "friendship_status": {
                      "following": false,
                      "muting": false,
                      "blocking": null
                    },
                    "pk": "45512948387",
                    "transparency_label": null,
                    "transparency_product": null,
                    "transparency_product_enabled": false,
                    "is_verified": true,
                    "id": null,
                    "text_post_app_is_private": false
                  },
                  "accessibility_caption": "Photo by Battle.net on July 10, 2023.",
                  "image_versions2": {
                    "candidates": [
                      {
                        "height": 1080,
                        "url": "https://scontent.cdninstagram.com/v/t51.2885-15/358798677_1097641387879584_452532359435037861_n.jpg?stp=dst-jpg_e35&efg=eyJ2ZW5jb2RlX3RhZyI6ImltYWdlX3VybGdlbi4xMDgweDEwODAuc2RyIn0&_nc_ht=scontent.cdninstagram.com&_nc_cat=100&_nc_ohc=tlgMpnqwKlgAX9BWG8R&edm=APs17CUBAAAA&ccb=7-5&ig_cache_key=MzE0NDA3NDEzNjkwNjI4OTgzOA%3D%3D.2-ccb7-5&oh=00_AfBy2Pa-6qWmXgAvOi77Uz97lLMZLF8lEtEpWpYZpx9qfQ&oe=6530C642&_nc_sid=10d13b",
                        "width": 1080
                      },
                      {
                        "height": 720,
                        "url": "https://scontent.cdninstagram.com/v/t51.2885-15/358798677_1097641387879584_452532359435037861_n.jpg?stp=dst-jpg_e35_s720x720&efg=eyJ2ZW5jb2RlX3RhZyI6ImltYWdlX3VybGdlbi4xMDgweDEwODAuc2RyIn0&_nc_ht=scontent.cdninstagram.com&_nc_cat=100&_nc_ohc=tlgMpnqwKlgAX9BWG8R&edm=APs17CUBAAAA&ccb=7-5&ig_cache_key=MzE0NDA3NDEzNjkwNjI4OTgzOA%3D%3D.2-ccb7-5&oh=00_AfDtHEtbWWQZHV30ji_7YDs1BRZhbNDqSlPXqTSGICsyDg&oe=6530C642&_nc_sid=10d13b",
                        "width": 720
                      },
                      {
                        "height": 640,
                        "url": "https://scontent.cdninstagram.com/v/t51.2885-15/358798677_1097641387879584_452532359435037861_n.jpg?stp=dst-jpg_e35_s640x640_sh0.08&efg=eyJ2ZW5jb2RlX3RhZyI6ImltYWdlX3VybGdlbi4xMDgweDEwODAuc2RyIn0&_nc_ht=scontent.cdninstagram.com&_nc_cat=100&_nc_ohc=tlgMpnqwKlgAX9BWG8R&edm=APs17CUBAAAA&ccb=7-5&ig_cache_key=MzE0NDA3NDEzNjkwNjI4OTgzOA%3D%3D.2-ccb7-5&oh=00_AfAOfkmXwHQAI_Ku15Cc4NeJfy6ceouaWA2_C4XcAt8cFA&oe=6530C642&_nc_sid=10d13b",
                        "width": 640
                      },
                      {
                        "height": 480,
                        "url": "https://scontent.cdninstagram.com/v/t51.2885-15/358798677_1097641387879584_452532359435037861_n.jpg?stp=dst-jpg_e35_s480x480&efg=eyJ2ZW5jb2RlX3RhZyI6ImltYWdlX3VybGdlbi4xMDgweDEwODAuc2RyIn0&_nc_ht=scontent.cdninstagram.com&_nc_cat=100&_nc_ohc=tlgMpnqwKlgAX9BWG8R&edm=APs17CUBAAAA&ccb=7-5&ig_cache_key=MzE0NDA3NDEzNjkwNjI4OTgzOA%3D%3D.2-ccb7-5&oh=00_AfD-n_zaiQiAGXEl5-ro6ARR3T6jUxW3qN5BalE-2we_Jg&oe=6530C642&_nc_sid=10d13b",
                        "width": 480
                      },
                      {
                        "height": 320,
                        "url": "https://scontent.cdninstagram.com/v/t51.2885-15/358798677_1097641387879584_452532359435037861_n.jpg?stp=dst-jpg_e35_s320x320&efg=eyJ2ZW5jb2RlX3RhZyI6ImltYWdlX3VybGdlbi4xMDgweDEwODAuc2RyIn0&_nc_ht=scontent.cdninstagram.com&_nc_cat=100&_nc_ohc=tlgMpnqwKlgAX9BWG8R&edm=APs17CUBAAAA&ccb=7-5&ig_cache_key=MzE0NDA3NDEzNjkwNjI4OTgzOA%3D%3D.2-ccb7-5&oh=00_AfAUu4Oyq4nWRM6DPOyUJrz3UcNGqFNjjU-WqeI3dJfL2Q&oe=6530C642&_nc_sid=10d13b",
                        "width": 320
                      },
                      {
                        "height": 240,
                        "url": "https://scontent.cdninstagram.com/v/t51.2885-15/358798677_1097641387879584_452532359435037861_n.jpg?stp=dst-jpg_e35_s240x240&efg=eyJ2ZW5jb2RlX3RhZyI6ImltYWdlX3VybGdlbi4xMDgweDEwODAuc2RyIn0&_nc_ht=scontent.cdninstagram.com&_nc_cat=100&_nc_ohc=tlgMpnqwKlgAX9BWG8R&edm=APs17CUBAAAA&ccb=7-5&ig_cache_key=MzE0NDA3NDEzNjkwNjI4OTgzOA%3D%3D.2-ccb7-5&oh=00_AfCW3O55z4lXiN80Cw2mQo2p4qWUPY5KQnlEYzQ6yMCr4Q&oe=6530C642&_nc_sid=10d13b",
                        "width": 240
                      },
                      {
                        "height": 1080,
                        "url": "https://scontent.cdninstagram.com/v/t51.2885-15/358798677_1097641387879584_452532359435037861_n.jpg?stp=dst-jpg_e35&efg=eyJ2ZW5jb2RlX3RhZyI6ImltYWdlX3VybGdlbi4xMDgweDEwODAuc2RyIn0&_nc_ht=scontent.cdninstagram.com&_nc_cat=100&_nc_ohc=tlgMpnqwKlgAX9BWG8R&edm=APs17CUBAAAA&ccb=7-5&ig_cache_key=MzE0NDA3NDEzNjkwNjI4OTgzOA%3D%3D.2-ccb7-5&oh=00_AfBy2Pa-6qWmXgAvOi77Uz97lLMZLF8lEtEpWpYZpx9qfQ&oe=6530C642&_nc_sid=10d13b",
                        "width": 1080
                      },
                      {
                        "height": 750,
                        "url": "https://scontent.cdninstagram.com/v/t51.2885-15/358798677_1097641387879584_452532359435037861_n.jpg?stp=dst-jpg_e35_s750x750_sh0.08&efg=eyJ2ZW5jb2RlX3RhZyI6ImltYWdlX3VybGdlbi4xMDgweDEwODAuc2RyIn0&_nc_ht=scontent.cdninstagram.com&_nc_cat=100&_nc_ohc=tlgMpnqwKlgAX9BWG8R&edm=APs17CUBAAAA&ccb=7-5&ig_cache_key=MzE0NDA3NDEzNjkwNjI4OTgzOA%3D%3D.2-ccb7-5&oh=00_AfCQmoeiR-jj_zmxt_uivL0ExQNgItmDD9QLhfkBhmIgMQ&oe=6530C642&_nc_sid=10d13b",
                        "width": 750
                      },
                      {
                        "height": 640,
                        "url": "https://scontent.cdninstagram.com/v/t51.2885-15/358798677_1097641387879584_452532359435037861_n.jpg?stp=dst-jpg_e35_s640x640_sh0.08&efg=eyJ2ZW5jb2RlX3RhZyI6ImltYWdlX3VybGdlbi4xMDgweDEwODAuc2RyIn0&_nc_ht=scontent.cdninstagram.com&_nc_cat=100&_nc_ohc=tlgMpnqwKlgAX9BWG8R&edm=APs17CUBAAAA&ccb=7-5&ig_cache_key=MzE0NDA3NDEzNjkwNjI4OTgzOA%3D%3D.2-ccb7-5&oh=00_AfAOfkmXwHQAI_Ku15Cc4NeJfy6ceouaWA2_C4XcAt8cFA&oe=6530C642&_nc_sid=10d13b",
                        "width": 640
                      },
                      {
                        "height": 480,
                        "url": "https://scontent.cdninstagram.com/v/t51.2885-15/358798677_1097641387879584_452532359435037861_n.jpg?stp=dst-jpg_e35_s480x480&efg=eyJ2ZW5jb2RlX3RhZyI6ImltYWdlX3VybGdlbi4xMDgweDEwODAuc2RyIn0&_nc_ht=scontent.cdninstagram.com&_nc_cat=100&_nc_ohc=tlgMpnqwKlgAX9BWG8R&edm=APs17CUBAAAA&ccb=7-5&ig_cache_key=MzE0NDA3NDEzNjkwNjI4OTgzOA%3D%3D.2-ccb7-5&oh=00_AfD-n_zaiQiAGXEl5-ro6ARR3T6jUxW3qN5BalE-2we_Jg&oe=6530C642&_nc_sid=10d13b",
                        "width": 480
                      },
                      {
                        "height": 320,
                        "url": "https://scontent.cdninstagram.com/v/t51.2885-15/358798677_1097641387879584_452532359435037861_n.jpg?stp=dst-jpg_e35_s320x320&efg=eyJ2ZW5jb2RlX3RhZyI6ImltYWdlX3VybGdlbi4xMDgweDEwODAuc2RyIn0&_nc_ht=scontent.cdninstagram.com&_nc_cat=100&_nc_ohc=tlgMpnqwKlgAX9BWG8R&edm=APs17CUBAAAA&ccb=7-5&ig_cache_key=MzE0NDA3NDEzNjkwNjI4OTgzOA%3D%3D.2-ccb7-5&oh=00_AfAUu4Oyq4nWRM6DPOyUJrz3UcNGqFNjjU-WqeI3dJfL2Q&oe=6530C642&_nc_sid=10d13b",
                        "width": 320
                      },
                      {
                        "height": 240,
                        "url": "https://scontent.cdninstagram.com/v/t51.2885-15/358798677_1097641387879584_452532359435037861_n.jpg?stp=dst-jpg_e35_s240x240&efg=eyJ2ZW5jb2RlX3RhZyI6ImltYWdlX3VybGdlbi4xMDgweDEwODAuc2RyIn0&_nc_ht=scontent.cdninstagram.com&_nc_cat=100&_nc_ohc=tlgMpnqwKlgAX9BWG8R&edm=APs17CUBAAAA&ccb=7-5&ig_cache_key=MzE0NDA3NDEzNjkwNjI4OTgzOA%3D%3D.2-ccb7-5&oh=00_AfCW3O55z4lXiN80Cw2mQo2p4qWUPY5KQnlEYzQ6yMCr4Q&oe=6530C642&_nc_sid=10d13b",
                        "width": 240
                      },
                      {
                        "height": 150,
                        "url": "https://scontent.cdninstagram.com/v/t51.2885-15/358798677_1097641387879584_452532359435037861_n.jpg?stp=dst-jpg_e35_s150x150&efg=eyJ2ZW5jb2RlX3RhZyI6ImltYWdlX3VybGdlbi4xMDgweDEwODAuc2RyIn0&_nc_ht=scontent.cdninstagram.com&_nc_cat=100&_nc_ohc=tlgMpnqwKlgAX9BWG8R&edm=APs17CUBAAAA&ccb=7-5&ig_cache_key=MzE0NDA3NDEzNjkwNjI4OTgzOA%3D%3D.2-ccb7-5&oh=00_AfCAjVFJNf47IlOot0WlROTS6idru1_N-QkEJgiEBrf70w&oe=6530C642&_nc_sid=10d13b",
                        "width": 150
                      }
                    ]
                  },
                  "original_width": 1080,
                  "original_height": 1080,
                  "code": "Cuh_sT9ytKu",
                  "video_versions": null,
                  "carousel_media": null,
                  "pk": "3144074136906289838",
                  "text_post_app_info": {
                    "share_info": {
                      "can_quote_post": true,
                      "can_repost": true,
                      "is_reposted_by_viewer": false,
                      "repost_restricted_reason": null,
                      "__typename": "XDTShareInfo",
                      "reposted_post": null,
                      "quoted_post": null
                    },
                    "can_reply": true,
                    "is_reply": false,
                    "hush_info": null,
                    "reply_control": "everyone",
                    "pinned_post_info": null,
                    "link_preview_attachment": null,
                    "reply_to_author": null,
                    "is_post_unavailable": false,
                    "post_unavailable_reason": null
                  },
                  "is_fb_only": null,
                  "is_internal_only": null,
                  "id": "3144074136906289838_45512948387",
                  "media_type": 1,
                  "has_audio": null,
                  "audio": null,
                  "transcription_data": null,
                  "caption_is_edited": false,
                  "has_liked": false,
                  "is_paid_partnership": null,
                  "like_and_view_counts_disabled": false,
                  "taken_at": 1689022865,
                  "caption": {
                    "text": "Battle.net account security just leveled up. Authenticate your logins, browse the Shop, and stay connected with friends, all via the Battle.net mobile app.\n\nCheck out the update now!\n\niOS âž¡ï¸ blizz.ly/3pvnx1J\nAndroid âž¡ï¸ blizz.ly/46BMBF4"
                  },
                  "like_count": 68,
                  "media_overlay_info": null
                },
                "line_type": "line",
                "view_replies_cta_string": "1 respuesta",
                "reply_facepile_users": [
                  {
                    "__typename": "XDTUserDict",
                    "id": null,
                    "profile_pic_url": "https://scontent.cdninstagram.com/v/t51.2885-19/387693460_1287635419303259_2130191439715928895_n.jpg?stp=dst-jpg_s150x150&_nc_ht=scontent.cdninstagram.com&_nc_cat=111&_nc_ohc=99CwvAIguxUAX_7gR7-&edm=APs17CUBAAAA&ccb=7-5&oh=00_AfCu2nOS-Vy_J08-zwnWsnEnMgxhklL6KlSiTEMfGEQPyw&oe=65317D61&_nc_sid=10d13b"
                  }
                ],
                "should_show_replies_cta": true,
                "__typename": "XDTThreadItem"
              }
            ],
            "id": "3144074136906289838",
            "__typename": "XDTThread"
          },
          "__typename": "XDTUserTextPostsResponseEdge",
          "cursor": ""
        },
        {
          "node": {
            "thread_items": [
              {
                "post": {
                  "user": {
                    "profile_pic_url": "https://scontent.cdninstagram.com/v/t51.2885-19/358342896_134138973038748_2871278261242540091_n.jpg?stp=dst-jpg_s150x150&_nc_ht=scontent.cdninstagram.com&_nc_cat=100&_nc_ohc=fnBk02x8fYYAX8m4UPS&edm=APs17CUBAAAA&ccb=7-5&oh=00_AfA9CiG3KzCtGkFuFfszkuUxpvtz7Btl_s53wbX5i2ADsw&oe=6531BE5A&_nc_sid=10d13b",
                    "username": "battlenet",
                    "friendship_status": {
                      "following": false,
                      "muting": false,
                      "blocking": null
                    },
                    "pk": "45512948387",
                    "transparency_label": null,
                    "transparency_product": null,
                    "transparency_product_enabled": false,
                    "is_verified": true,
                    "id": null,
                    "text_post_app_is_private": false
                  },
                  "accessibility_caption": "Photo by Battle.net on July 07, 2023.",
                  "image_versions2": {
                    "candidates": [
                      {
                        "height": 1080,
                        "url": "https://scontent.cdninstagram.com/v/t51.2885-15/358333584_809996183842666_7682180217326468643_n.jpg?stp=dst-jpg_e35&efg=eyJ2ZW5jb2RlX3RhZyI6ImltYWdlX3VybGdlbi4xOTIweDEwODAuc2RyIn0&_nc_ht=scontent.cdninstagram.com&_nc_cat=110&_nc_ohc=sFVxRUxlSGcAX9qAotv&edm=APs17CUBAAAA&ccb=7-5&ig_cache_key=MzE0MTk2MTA3MjM4NzA1MDUwNQ%3D%3D.2-ccb7-5&oh=00_AfA_L2qFnvbwjcjOY1RSsBOadebGx3UohqyXhSL1Y0i7tg&oe=653095D9&_nc_sid=10d13b",
                        "width": 1920
                      },
                      {
                        "height": 608,
                        "url": "https://scontent.cdninstagram.com/v/t51.2885-15/358333584_809996183842666_7682180217326468643_n.jpg?stp=dst-jpg_e35_s1080x1080&efg=eyJ2ZW5jb2RlX3RhZyI6ImltYWdlX3VybGdlbi4xOTIweDEwODAuc2RyIn0&_nc_ht=scontent.cdninstagram.com&_nc_cat=110&_nc_ohc=sFVxRUxlSGcAX9qAotv&edm=APs17CUBAAAA&ccb=7-5&ig_cache_key=MzE0MTk2MTA3MjM4NzA1MDUwNQ%3D%3D.2-ccb7-5&oh=00_AfDuB17EOgPcREmlcEVQMkhUTKCZRziACsPKDDEKi8OP9Q&oe=653095D9&_nc_sid=10d13b",
                        "width": 1080
                      },
                      {
                        "height": 405,
                        "url": "https://scontent.cdninstagram.com/v/t51.2885-15/358333584_809996183842666_7682180217326468643_n.jpg?stp=dst-jpg_e35_s720x720&efg=eyJ2ZW5jb2RlX3RhZyI6ImltYWdlX3VybGdlbi4xOTIweDEwODAuc2RyIn0&_nc_ht=scontent.cdninstagram.com&_nc_cat=110&_nc_ohc=sFVxRUxlSGcAX9qAotv&edm=APs17CUBAAAA&ccb=7-5&ig_cache_key=MzE0MTk2MTA3MjM4NzA1MDUwNQ%3D%3D.2-ccb7-5&oh=00_AfBh31BKq3imbIe6GzZIpOYH5wiuDLcUWySdbdT-jntPSw&oe=653095D9&_nc_sid=10d13b",
                        "width": 720
                      },
                      {
                        "height": 360,
                        "url": "https://scontent.cdninstagram.com/v/t51.2885-15/358333584_809996183842666_7682180217326468643_n.jpg?stp=dst-jpg_e35_s640x640_sh0.08&efg=eyJ2ZW5jb2RlX3RhZyI6ImltYWdlX3VybGdlbi4xOTIweDEwODAuc2RyIn0&_nc_ht=scontent.cdninstagram.com&_nc_cat=110&_nc_ohc=sFVxRUxlSGcAX9qAotv&edm=APs17CUBAAAA&ccb=7-5&ig_cache_key=MzE0MTk2MTA3MjM4NzA1MDUwNQ%3D%3D.2-ccb7-5&oh=00_AfBVDBrkEkwdgkG088Oa9FaM1V7AOpXqdeAiGh4ykE55zg&oe=653095D9&_nc_sid=10d13b",
                        "width": 640
                      },
                      {
                        "height": 270,
                        "url": "https://scontent.cdninstagram.com/v/t51.2885-15/358333584_809996183842666_7682180217326468643_n.jpg?stp=dst-jpg_e35_s480x480&efg=eyJ2ZW5jb2RlX3RhZyI6ImltYWdlX3VybGdlbi4xOTIweDEwODAuc2RyIn0&_nc_ht=scontent.cdninstagram.com&_nc_cat=110&_nc_ohc=sFVxRUxlSGcAX9qAotv&edm=APs17CUBAAAA&ccb=7-5&ig_cache_key=MzE0MTk2MTA3MjM4NzA1MDUwNQ%3D%3D.2-ccb7-5&oh=00_AfB8_EvC3ARXAkzmplbK972sEdjAabWC3HfnXKZOncGs3w&oe=653095D9&_nc_sid=10d13b",
                        "width": 480
                      },
                      {
                        "height": 180,
                        "url": "https://scontent.cdninstagram.com/v/t51.2885-15/358333584_809996183842666_7682180217326468643_n.jpg?stp=dst-jpg_e35_s320x320&efg=eyJ2ZW5jb2RlX3RhZyI6ImltYWdlX3VybGdlbi4xOTIweDEwODAuc2RyIn0&_nc_ht=scontent.cdninstagram.com&_nc_cat=110&_nc_ohc=sFVxRUxlSGcAX9qAotv&edm=APs17CUBAAAA&ccb=7-5&ig_cache_key=MzE0MTk2MTA3MjM4NzA1MDUwNQ%3D%3D.2-ccb7-5&oh=00_AfBZKZcShoLbb3R5ZyyvoCKZZWa5517LMdhC46ENNO34TQ&oe=653095D9&_nc_sid=10d13b",
                        "width": 320
                      },
                      {
                        "height": 135,
                        "url": "https://scontent.cdninstagram.com/v/t51.2885-15/358333584_809996183842666_7682180217326468643_n.jpg?stp=dst-jpg_e35_s240x240&efg=eyJ2ZW5jb2RlX3RhZyI6ImltYWdlX3VybGdlbi4xOTIweDEwODAuc2RyIn0&_nc_ht=scontent.cdninstagram.com&_nc_cat=110&_nc_ohc=sFVxRUxlSGcAX9qAotv&edm=APs17CUBAAAA&ccb=7-5&ig_cache_key=MzE0MTk2MTA3MjM4NzA1MDUwNQ%3D%3D.2-ccb7-5&oh=00_AfB1hEQFeph8yIen1psjgoll7g9BtvDZfClEsZ01TOgdxA&oe=653095D9&_nc_sid=10d13b",
                        "width": 240
                      },
                      {
                        "height": 1080,
                        "url": "https://scontent.cdninstagram.com/v/t51.2885-15/358333584_809996183842666_7682180217326468643_n.jpg?stp=c420.0.1080.1080a_dst-jpg_e35_s1080x1080&efg=eyJ2ZW5jb2RlX3RhZyI6ImltYWdlX3VybGdlbi4xOTIweDEwODAuc2RyIn0&_nc_ht=scontent.cdninstagram.com&_nc_cat=110&_nc_ohc=sFVxRUxlSGcAX9qAotv&edm=APs17CUBAAAA&ccb=7-5&ig_cache_key=MzE0MTk2MTA3MjM4NzA1MDUwNQ%3D%3D.2-ccb7-5&oh=00_AfDihIXC39PXHgWyQWUGwMjItBVnpIHkG5IhrUc5NGmgQA&oe=653095D9&_nc_sid=10d13b",
                        "width": 1080
                      },
                      {
                        "height": 750,
                        "url": "https://scontent.cdninstagram.com/v/t51.2885-15/358333584_809996183842666_7682180217326468643_n.jpg?stp=c420.0.1080.1080a_dst-jpg_e35_s750x750_sh0.08&efg=eyJ2ZW5jb2RlX3RhZyI6ImltYWdlX3VybGdlbi4xOTIweDEwODAuc2RyIn0&_nc_ht=scontent.cdninstagram.com&_nc_cat=110&_nc_ohc=sFVxRUxlSGcAX9qAotv&edm=APs17CUBAAAA&ccb=7-5&ig_cache_key=MzE0MTk2MTA3MjM4NzA1MDUwNQ%3D%3D.2-ccb7-5&oh=00_AfB26tdFf6johmOyo0fYT1ZiUA_h9H1WmB_vWVpXqM550w&oe=653095D9&_nc_sid=10d13b",
                        "width": 750
                      },
                      {
                        "height": 640,
                        "url": "https://scontent.cdninstagram.com/v/t51.2885-15/358333584_809996183842666_7682180217326468643_n.jpg?stp=c420.0.1080.1080a_dst-jpg_e35_s640x640_sh0.08&efg=eyJ2ZW5jb2RlX3RhZyI6ImltYWdlX3VybGdlbi4xOTIweDEwODAuc2RyIn0&_nc_ht=scontent.cdninstagram.com&_nc_cat=110&_nc_ohc=sFVxRUxlSGcAX9qAotv&edm=APs17CUBAAAA&ccb=7-5&ig_cache_key=MzE0MTk2MTA3MjM4NzA1MDUwNQ%3D%3D.2-ccb7-5&oh=00_AfAckAYJUyb8LGxP9f6IwRXYOrElgU3ugxcHb0N8Nnxizw&oe=653095D9&_nc_sid=10d13b",
                        "width": 640
                      },
                      {
                        "height": 480,
                        "url": "https://scontent.cdninstagram.com/v/t51.2885-15/358333584_809996183842666_7682180217326468643_n.jpg?stp=c420.0.1080.1080a_dst-jpg_e35_s480x480&efg=eyJ2ZW5jb2RlX3RhZyI6ImltYWdlX3VybGdlbi4xOTIweDEwODAuc2RyIn0&_nc_ht=scontent.cdninstagram.com&_nc_cat=110&_nc_ohc=sFVxRUxlSGcAX9qAotv&edm=APs17CUBAAAA&ccb=7-5&ig_cache_key=MzE0MTk2MTA3MjM4NzA1MDUwNQ%3D%3D.2-ccb7-5&oh=00_AfBmgIsCW7NIGA1Mj9Dd1zmmf-GSdmgHxVJjdBLMP7PZHA&oe=653095D9&_nc_sid=10d13b",
                        "width": 480
                      },
                      {
                        "height": 320,
                        "url": "https://scontent.cdninstagram.com/v/t51.2885-15/358333584_809996183842666_7682180217326468643_n.jpg?stp=c420.0.1080.1080a_dst-jpg_e35_s320x320&efg=eyJ2ZW5jb2RlX3RhZyI6ImltYWdlX3VybGdlbi4xOTIweDEwODAuc2RyIn0&_nc_ht=scontent.cdninstagram.com&_nc_cat=110&_nc_ohc=sFVxRUxlSGcAX9qAotv&edm=APs17CUBAAAA&ccb=7-5&ig_cache_key=MzE0MTk2MTA3MjM4NzA1MDUwNQ%3D%3D.2-ccb7-5&oh=00_AfA_vid9Irw2vXdWZkh-FRDdmE7a52HmBxLzPUsKM8axJA&oe=653095D9&_nc_sid=10d13b",
                        "width": 320
                      },
                      {
                        "height": 240,
                        "url": "https://scontent.cdninstagram.com/v/t51.2885-15/358333584_809996183842666_7682180217326468643_n.jpg?stp=c420.0.1080.1080a_dst-jpg_e35_s240x240&efg=eyJ2ZW5jb2RlX3RhZyI6ImltYWdlX3VybGdlbi4xOTIweDEwODAuc2RyIn0&_nc_ht=scontent.cdninstagram.com&_nc_cat=110&_nc_ohc=sFVxRUxlSGcAX9qAotv&edm=APs17CUBAAAA&ccb=7-5&ig_cache_key=MzE0MTk2MTA3MjM4NzA1MDUwNQ%3D%3D.2-ccb7-5&oh=00_AfCSF6b-JnHKltTyLcKy083KT52bYzIr1jT6ZJtkUYI9Yg&oe=653095D9&_nc_sid=10d13b",
                        "width": 240
                      },
                      {
                        "height": 150,
                        "url": "https://scontent.cdninstagram.com/v/t51.2885-15/358333584_809996183842666_7682180217326468643_n.jpg?stp=c420.0.1080.1080a_dst-jpg_e35_s150x150&efg=eyJ2ZW5jb2RlX3RhZyI6ImltYWdlX3VybGdlbi4xOTIweDEwODAuc2RyIn0&_nc_ht=scontent.cdninstagram.com&_nc_cat=110&_nc_ohc=sFVxRUxlSGcAX9qAotv&edm=APs17CUBAAAA&ccb=7-5&ig_cache_key=MzE0MTk2MTA3MjM4NzA1MDUwNQ%3D%3D.2-ccb7-5&oh=00_AfADWUOxIsDavk3yqkVff-_MoeKXQ6bHjF8kEUniOclc5Q&oe=653095D9&_nc_sid=10d13b",
                        "width": 150
                      }
                    ]
                  },
                  "original_width": 1920,
                  "original_height": 1080,
                  "code": "CuafPLRvEwJ",
                  "video_versions": null,
                  "carousel_media": null,
                  "pk": "3141961072387050505",
                  "text_post_app_info": {
                    "share_info": {
                      "can_quote_post": true,
                      "can_repost": true,
                      "is_reposted_by_viewer": false,
                      "repost_restricted_reason": null,
                      "__typename": "XDTShareInfo",
                      "reposted_post": null,
                      "quoted_post": null
                    },
                    "can_reply": true,
                    "is_reply": false,
                    "hush_info": null,
                    "reply_control": "everyone",
                    "pinned_post_info": null,
                    "link_preview_attachment": null,
                    "reply_to_author": null,
                    "is_post_unavailable": false,
                    "post_unavailable_reason": null
                  },
                  "is_fb_only": null,
                  "is_internal_only": null,
                  "id": "3141961072387050505_45512948387",
                  "media_type": 1,
                  "has_audio": null,
                  "audio": null,
                  "transcription_data": null,
                  "caption_is_edited": false,
                  "has_liked": false,
                  "is_paid_partnership": null,
                  "like_and_view_counts_disabled": false,
                  "taken_at": 1688770968,
                  "caption": {
                    "text": "Whelp Daycare > all other responsibilities ðŸ‰\n\nThoughts?"
                  },
                  "like_count": 288,
                  "media_overlay_info": null
                },
                "line_type": "line",
                "view_replies_cta_string": "19 respuestas",
                "reply_facepile_users": [
                  {
                    "__typename": "XDTUserDict",
                    "id": null,
                    "profile_pic_url": "https://scontent.cdninstagram.com/v/t51.2885-19/358520760_1737598233412488_3757108396120908546_n.jpg?stp=dst-jpg_s150x150&_nc_ht=scontent.cdninstagram.com&_nc_cat=100&_nc_ohc=kmbTgdR_1ekAX88suba&edm=APs17CUBAAAA&ccb=7-5&oh=00_AfC5lnYmztgLNcu_xQUL7EWdvJEXaS57LP8lWNNV2wc5QA&oe=65329796&_nc_sid=10d13b"
                  },
                  {
                    "__typename": "XDTUserDict",
                    "id": null,
                    "profile_pic_url": "https://scontent.cdninstagram.com/v/t51.2885-19/357997431_227520303560407_8243888173205454149_n.jpg?stp=dst-jpg_s150x150&_nc_ht=scontent.cdninstagram.com&_nc_cat=107&_nc_ohc=6IFZgYq_h9IAX-4AwKl&edm=APs17CUBAAAA&ccb=7-5&oh=00_AfDXUdtHzHnf3y_m3xOFbtN1a2qxlld--9Er3yYSb1f2KQ&oe=65317720&_nc_sid=10d13b"
                  }
                ],
                "should_show_replies_cta": true,
                "__typename": "XDTThreadItem"
              }
            ],
            "id": "3141961072387050505",
            "__typename": "XDTThread"
          },
          "__typename": "XDTUserTextPostsResponseEdge",
          "cursor": ""
        },
        {
          "node": {
            "thread_items": [
              {
                "post": {
                  "user": {
                    "profile_pic_url": "https://scontent.cdninstagram.com/v/t51.2885-19/358342896_134138973038748_2871278261242540091_n.jpg?stp=dst-jpg_s150x150&_nc_ht=scontent.cdninstagram.com&_nc_cat=100&_nc_ohc=fnBk02x8fYYAX8m4UPS&edm=APs17CUBAAAA&ccb=7-5&oh=00_AfA9CiG3KzCtGkFuFfszkuUxpvtz7Btl_s53wbX5i2ADsw&oe=6531BE5A&_nc_sid=10d13b",
                    "username": "battlenet",
                    "friendship_status": {
                      "following": false,
                      "muting": false,
                      "blocking": null
                    },
                    "pk": "45512948387",
                    "transparency_label": null,
                    "transparency_product": null,
                    "transparency_product_enabled": false,
                    "is_verified": true,
                    "id": null,
                    "text_post_app_is_private": false
                  },
                  "accessibility_caption": null,
                  "image_versions2": {
                    "candidates": []
                  },
                  "original_width": 612,
                  "original_height": 612,
                  "code": "CuVbIsOvZRC",
                  "video_versions": null,
                  "carousel_media": null,
                  "pk": "3140535659664348226",
                  "text_post_app_info": {
                    "share_info": {
                      "can_quote_post": true,
                      "can_repost": true,
                      "is_reposted_by_viewer": false,
                      "repost_restricted_reason": null,
                      "__typename": "XDTShareInfo",
                      "reposted_post": null,
                      "quoted_post": null
                    },
                    "can_reply": true,
                    "is_reply": false,
                    "hush_info": null,
                    "reply_control": "everyone",
                    "pinned_post_info": null,
                    "link_preview_attachment": null,
                    "reply_to_author": null,
                    "is_post_unavailable": false,
                    "post_unavailable_reason": null
                  },
                  "is_fb_only": null,
                  "is_internal_only": null,
                  "id": "3140535659664348226_45512948387",
                  "media_type": 19,
                  "has_audio": null,
                  "audio": null,
                  "transcription_data": null,
                  "caption_is_edited": false,
                  "has_liked": false,
                  "is_paid_partnership": null,
                  "like_and_view_counts_disabled": false,
                  "taken_at": 1688601046,
                  "caption": {
                    "text": "What Battle.net game is everyone playing tonight?"
                  },
                  "like_count": 443,
                  "media_overlay_info": null
                },
                "line_type": "line",
                "view_replies_cta_string": "264 respuestas",
                "reply_facepile_users": [
                  {
                    "__typename": "XDTUserDict",
                    "id": null,
                    "profile_pic_url": "https://scontent.cdninstagram.com/v/t51.2885-19/358349210_1317147735863636_8043386364993478775_n.jpg?stp=dst-jpg_s150x150&_nc_ht=scontent.cdninstagram.com&_nc_cat=108&_nc_ohc=06EgRl1gfHAAX91jiUY&edm=APs17CUBAAAA&ccb=7-5&oh=00_AfCtd30OnHd7Zq73jytYNMN7ZSXRrcG6eLKRvd4j9UdUrA&oe=6532348C&_nc_sid=10d13b"
                  },
                  {
                    "__typename": "XDTUserDict",
                    "id": null,
                    "profile_pic_url": "https://scontent.cdninstagram.com/v/t51.2885-19/358362050_973333733817720_3759548566867577037_n.jpg?stp=dst-jpg_s150x150&_nc_ht=scontent.cdninstagram.com&_nc_cat=100&_nc_ohc=ODkP76IG6iEAX-ZFwkp&edm=APs17CUBAAAA&ccb=7-5&oh=00_AfB5EWzfO4RXm3llSjnSzHmCoc9pviDMd0_OcoBU_V2rDQ&oe=65319905&_nc_sid=10d13b"
                  },
                  {
                    "__typename": "XDTUserDict",
                    "id": null,
                    "profile_pic_url": "https://scontent.cdninstagram.com/v/t51.2885-19/368676172_127840923731010_685345786751946045_n.jpg?stp=dst-jpg_s150x150&_nc_ht=scontent.cdninstagram.com&_nc_cat=106&_nc_ohc=xJjXfdEMF3gAX_IeOua&edm=APs17CUBAAAA&ccb=7-5&oh=00_AfCy6sPiYBLGhVKiseX_DrawCK3LYkD0H38XX3T0DP9d8w&oe=65321FB3&_nc_sid=10d13b"
                  }
                ],
                "should_show_replies_cta": true,
                "__typename": "XDTThreadItem"
              }
            ],
            "id": "3140535659664348226",
            "__typename": "XDTThread"
          },
          "__typename": "XDTUserTextPostsResponseEdge",
          "cursor": ""
        }
      ],
      "page_info": {
        "end_cursor": null,
        "has_next_page": false,
        "has_previous_page": false,
        "start_cursor": null
      }
    },
    "hideLikesSettingData": {
      "hide_like_and_view_counts": false
    }
  },
  "extensions": {
    "is_final": true
  }
}