{
  "data": {
    "userData": {
      "user": {
        "pk": "627248568",
        "username": "playstationes",
        "hd_profile_pic_versions": [
          {
            "height": 320,
            "url": "https://scontent.cdninstagram.com/v/t51.2885-19/358165438_9512378972166786_6028744780613568967_n.jpg?stp=dst-jpg_s320x320&_nc_ht=scontent.cdninstagram.com&_nc_cat=106&_nc_ohc=KNIgdTzTgbUAX8Pq87K&edm=APs17CUBAAAA&ccb=7-5&oh=00_AfC3wT8Tn7vpmZmqAFVU8r3wvPy71mgVjZrwlQ88zL6PmA&oe=65341A23&_nc_sid=10d13b",
            "width": 320
          },
          {
            "height": 640,
            "url": "https://scontent.cdninstagram.com/v/t51.2885-19/358165438_9512378972166786_6028744780613568967_n.jpg?stp=dst-jpg_s640x640&_nc_ht=scontent.cdninstagram.com&_nc_cat=106&_nc_ohc=KNIgdTzTgbUAX8Pq87K&edm=APs17CUBAAAA&ccb=7-5&oh=00_AfCM9yxLHsQTyvUBH0dMtYViPf0UjW8QsJiNfJ3Qalkc5g&oe=65341A23&_nc_sid=10d13b",
            "width": 640
          }
        ],
        "profile_pic_url": "https://scontent.cdninstagram.com/v/t51.2885-19/358165438_9512378972166786_6028744780613568967_n.jpg?stp=dst-jpg_s150x150&_nc_ht=scontent.cdninstagram.com&_nc_cat=106&_nc_ohc=KNIgdTzTgbUAX8Pq87K&edm=APs17CUBAAAA&ccb=7-5&oh=00_AfAyjd0ehfQtrEq8CweV5IUbOQ8dd1QJ6Pjo4gdXwdtTpQ&oe=65341A23&_nc_sid=10d13b",
        "friendship_status": {
          "is_restricted": false,
          "blocking": false,
          "muting": false,
          "followed_by": false,
          "following": false,
          "outgoing_request": false,
          "incoming_request": false
        },
        "follower_count": 54178,
        "profile_context_facepile_users": [],
        "is_verified": true,
        "biography": "¡Bienvenido al perfil oficial de PlayStation España! 🎮",
        "biography_with_entities": {
          "entities": [],
          "raw_text": "¡Bienvenido al perfil oficial de PlayStation España! 🎮"
        },
        "account_badges": [],
        "bio_links": [
          {
            "url": "https://bit.ly/m/PlayStationES"
          }
        ],
        "text_post_app_is_private": false,
        "transparency_label": null,
        "full_name": "PlayStation España",
        "text_post_app_remove_mention_entrypoint": false,
        "id": "627248568"
      }
    }
  },
  "extensions": {
    "is_final": true
  }
}